[
    {
        "text": "London Big Jocho\n41 min\n\u00b7\n$ 50.90",
        "href": "https://www.rappi.com.mx/restaurantes/1923795920-london-big-jocho",
        "cate_source": "populares_cerca",
        "current_address": "05710, Ciudad de M\u00e9xico",
        "final_address": "05710, Las Maromas, Cuajimalpa de Morelos\nCDMX, M\u00e9xico",
        "platform": "rappi"
    },
    {
        "text": "Taqueria Trompito Ayuukk\n36 min\n\u00b7\n$ 48.90",
        "href": "https://www.rappi.com.mx/restaurantes/1930016474-taqueria-trompito-ayuukk",
        "cate_source": "populares_cerca",
        "current_address": "05710, Ciudad de M\u00e9xico",
        "final_address": "05710, Las Maromas, Cuajimalpa de Morelos\nCDMX, M\u00e9xico",
        "platform": "rappi"
    },
    {
        "text": "Los Pozoles\n35 min\n\u00b7\n$ 14.90",
        "href": "https://www.rappi.com.mx/restaurantes/1930104629-los-pozoles",
        "cate_source": "populares_cerca",
        "current_address": "05710, Ciudad de M\u00e9xico",
        "final_address": "05710, Las Maromas, Cuajimalpa de Morelos\nCDMX, M\u00e9xico",
        "platform": "rappi"
    },
    {
        "text": "Tacos los Grandes\n35 min\n\u00b7\n$ 10.90",
        "href": "https://www.rappi.com.mx/restaurantes/1930104816-tacos-los-grandes",
        "cate_source": "populares_cerca",
        "current_address": "05710, Ciudad de M\u00e9xico",
        "final_address": "05710, Las Maromas, Cuajimalpa de Morelos\nCDMX, M\u00e9xico",
        "platform": "rappi"
    },
    {
        "text": "El Garage de Las Crepas\n35 min\n\u00b7\n$ 40.90",
        "href": "https://www.rappi.com.mx/restaurantes/1930109130-el-garage-de-las-crepas",
        "cate_source": "populares_cerca",
        "current_address": "05710, Ciudad de M\u00e9xico",
        "final_address": "05710, Las Maromas, Cuajimalpa de Morelos\nCDMX, M\u00e9xico",
        "platform": "rappi"
    },
    {
        "text": "Carnitas Chema\n35 min\n\u00b7\n$ 40.90",
        "href": "https://www.rappi.com.mx/restaurantes/1930172110-carnitas-chema",
        "cate_source": "populares_cerca",
        "current_address": "05710, Ciudad de M\u00e9xico",
        "final_address": "05710, Las Maromas, Cuajimalpa de Morelos\nCDMX, M\u00e9xico",
        "platform": "rappi"
    },
    {
        "text": "Restaurante El Amigo\n35 min\n\u00b7\n$ 30.90",
        "href": "https://www.rappi.com.mx/restaurantes/1923206371-restaurante-el-amigo",
        "cate_source": "populares_cerca",
        "current_address": "05710, Ciudad de M\u00e9xico",
        "final_address": "05710, Las Maromas, Cuajimalpa de Morelos\nCDMX, M\u00e9xico",
        "platform": "rappi"
    },
    {
        "text": "Barbacoa Estilo Capulhuac Mx\n35 min\n\u00b7\n$ 36.90",
        "href": "https://www.rappi.com.mx/restaurantes/1923814562-barbacoa-estilo-capulhuac-mx",
        "cate_source": "populares_cerca",
        "current_address": "05710, Ciudad de M\u00e9xico",
        "final_address": "05710, Las Maromas, Cuajimalpa de Morelos\nCDMX, M\u00e9xico",
        "platform": "rappi"
    },
    {
        "text": "Carnitas Rodeo Cuajimalpa\n35 min\n\u00b7\n$ 40.90",
        "href": "https://www.rappi.com.mx/restaurantes/1930095085-carnitas-rodeo-cuajimalpa",
        "cate_source": "populares_cerca",
        "current_address": "05710, Ciudad de M\u00e9xico",
        "final_address": "05710, Las Maromas, Cuajimalpa de Morelos\nCDMX, M\u00e9xico",
        "platform": "rappi"
    },
    {
        "text": "La Abela Tacos de Guisado\n35 min\n\u00b7\n$ 40.90",
        "href": "https://www.rappi.com.mx/restaurantes/1930095758-la-abela-tacos-de-guisado",
        "cate_source": "populares_cerca",
        "current_address": "05710, Ciudad de M\u00e9xico",
        "final_address": "05710, Las Maromas, Cuajimalpa de Morelos\nCDMX, M\u00e9xico",
        "platform": "rappi"
    },
    {
        "text": "El Caba\u00f1azo\n35 min\n\u00b7\n$ 34.90",
        "href": "https://www.rappi.com.mx/restaurantes/1930102502-el-cabanazo",
        "cate_source": "populares_cerca",
        "current_address": "05710, Ciudad de M\u00e9xico",
        "final_address": "05710, Las Maromas, Cuajimalpa de Morelos\nCDMX, M\u00e9xico",
        "platform": "rappi"
    },
    {
        "text": "El Rincon Del Sabor la Venta\n35 min\n\u00b7\n$ 30.90",
        "href": "https://www.rappi.com.mx/restaurantes/1930185207-el-rincon-del-sabor-la-venta",
        "cate_source": "populares_cerca",
        "current_address": "05710, Ciudad de M\u00e9xico",
        "final_address": "05710, Las Maromas, Cuajimalpa de Morelos\nCDMX, M\u00e9xico",
        "platform": "rappi"
    }
]