[
    {
        "text": "Tortas Gigantes Sur 12 Ermita\nTortas Gigantes Sur 12 Ermita\n4.6\n(8,000+)\n \u2022 \n10 min",
        "href": "https://www.ubereats.com/mx/store/tortas-gigantes-sur-12-ermita/PWW1ygseQyipWaNefyYi6w",
        "cate_source": "populares_cerca",
        "current_address": "09660, Ciudad de M\u00e9xico",
        "final_address": "09660\nCitlalli Ciudad de M\u00e9xico, CDMX, M\u00e9xico",
        "platform": "ubereats"
    },
    {
        "text": "China Food Wus\nChina Food Wus\n4.6\n(4,000+)\n \u2022 \n10 min",
        "href": "https://www.ubereats.com/mx/store/china-food-wus-ermita/rm0ztr6DSiW-cHcyo2jV_g",
        "cate_source": "populares_cerca",
        "current_address": "09660, Ciudad de M\u00e9xico",
        "final_address": "09660\nCitlalli Ciudad de M\u00e9xico, CDMX, M\u00e9xico",
        "platform": "ubereats"
    },
    {
        "text": "TACOS DON LUIS NEZA\nTACOS DON LUIS NEZA\n4.5\n(440+)\n \u2022 \n41 min",
        "href": "https://www.ubereats.com/mx/store/tacos-don-luis-neza/aKcytGXcSLGvz1N9ptx5WA",
        "cate_source": "populares_cerca",
        "current_address": "09660, Ciudad de M\u00e9xico",
        "final_address": "09660\nCitlalli Ciudad de M\u00e9xico, CDMX, M\u00e9xico",
        "platform": "ubereats"
    },
    {
        "text": "Super Caldos de Gallina Esnarlin\nSuper Caldos de Gallina Esnarlin\n4.7\n(3,000+)\n \u2022 \n13 min",
        "href": "https://www.ubereats.com/mx/store/super-caldos-de-gallina-esnarlin/PYt3SVkcRP-wf18MjSzs4w",
        "cate_source": "populares_cerca",
        "current_address": "09660, Ciudad de M\u00e9xico",
        "final_address": "09660\nCitlalli Ciudad de M\u00e9xico, CDMX, M\u00e9xico",
        "platform": "ubereats"
    },
    {
        "text": "Las Quekas Factory Santa Mar\u00eda Aztahuac\u00e1n\nLas Quekas Factory Santa Mar\u00eda Aztahuac\u00e1n\n4.5\n(2,000+)\n \u2022 \n14 min",
        "href": "https://www.ubereats.com/mx/store/las-quekas-factory-santa-maria-aztahuacan/KuF7CWODTt6Eajae9a8p-Q",
        "cate_source": "populares_cerca",
        "current_address": "09660, Ciudad de M\u00e9xico",
        "final_address": "09660\nCitlalli Ciudad de M\u00e9xico, CDMX, M\u00e9xico",
        "platform": "ubereats"
    },
    {
        "text": "Tortas Gigantes Sur 12\nTortas Gigantes Sur 12\n4.5\n(9,000+)\n \u2022 \n44 min",
        "href": "https://www.ubereats.com/mx/store/tortas-gigantes-sur-12-neza/-H7E02NiQPWhC3TKVbDM7A",
        "cate_source": "populares_cerca",
        "current_address": "09660, Ciudad de M\u00e9xico",
        "final_address": "09660\nCitlalli Ciudad de M\u00e9xico, CDMX, M\u00e9xico",
        "platform": "ubereats"
    },
    {
        "text": "Coyote Snacks\nCoyote Snacks\n4.5\n(900+)\n \u2022 \n14 min",
        "href": "https://www.ubereats.com/mx/store/coyote-snacks/wzyoEcCBSYmsi_T8LeJTXw",
        "cate_source": "populares_cerca",
        "current_address": "09660, Ciudad de M\u00e9xico",
        "final_address": "09660\nCitlalli Ciudad de M\u00e9xico, CDMX, M\u00e9xico",
        "platform": "ubereats"
    },
    {
        "text": "Super Burritos El Farolito\nSuper Burritos El Farolito\n4.6\n(700+)\n \u2022 \n10 min",
        "href": "https://www.ubereats.com/mx/store/super-burritos-el-farolito/tEt6VXn5RbSpVVy15ujjXg",
        "cate_source": "populares_cerca",
        "current_address": "09660, Ciudad de M\u00e9xico",
        "final_address": "09660\nCitlalli Ciudad de M\u00e9xico, CDMX, M\u00e9xico",
        "platform": "ubereats"
    },
    {
        "text": "Chucheriascdmx\nChucheriascdmx\n4.7\n(480+)\n \u2022 \n42 min",
        "href": "https://www.ubereats.com/mx/store/chucheriascdmx/hRb_Q1QQWpuO7oCID9D-qA",
        "cate_source": "populares_cerca",
        "current_address": "09660, Ciudad de M\u00e9xico",
        "final_address": "09660\nCitlalli Ciudad de M\u00e9xico, CDMX, M\u00e9xico",
        "platform": "ubereats"
    },
    {
        "text": "Pepe\u2019s House Grill & Drink\nPepe\u2019s House Grill & Drink\n4.6\n(500+)\n \u2022 \n16 min",
        "href": "https://www.ubereats.com/mx/store/pepes-house-grill-%26-drink/JBjjxORHQymFiBAz1wpJCw",
        "cate_source": "populares_cerca",
        "current_address": "09660, Ciudad de M\u00e9xico",
        "final_address": "09660\nCitlalli Ciudad de M\u00e9xico, CDMX, M\u00e9xico",
        "platform": "ubereats"
    },
    {
        "text": "Taquer\u00eda YAAXKIIN Los Alambres de la 23\nTaquer\u00eda YAAXKIIN Los Alambres de la 23\n4.7\n(1,500+)\n \u2022 \n30 min",
        "href": "https://www.ubereats.com/mx/store/taqueria-yaaxkiin-los-alambres-de-la-23/o04oiBGcRguSvCunU2oDZg",
        "cate_source": "populares_cerca",
        "current_address": "09660, Ciudad de M\u00e9xico",
        "final_address": "09660\nCitlalli Ciudad de M\u00e9xico, CDMX, M\u00e9xico",
        "platform": "ubereats"
    },
    {
        "text": "Alitas Black & Pink\nAhorros exclusivos\nAlitas Black & Pink\n4.3\n(270+)\n \u2022 \n41 min",
        "href": "https://www.ubereats.com/mx/store/alitas-black-%26-pink-mexico-city/GxdguSXyQSCYz4x8wmk5Uw",
        "cate_source": "populares_cerca",
        "current_address": "09660, Ciudad de M\u00e9xico",
        "final_address": "09660\nCitlalli Ciudad de M\u00e9xico, CDMX, M\u00e9xico",
        "platform": "ubereats"
    },
    {
        "text": "Pastes Kiko's\nPastes Kiko's\n4.7\n(210+)\n \u2022 \n25 min",
        "href": "https://www.ubereats.com/mx/store/pastes-kikos-iztapalapa/ugHgSyMGX_KN1q4SAozaNQ",
        "cate_source": "populares_cerca",
        "current_address": "09660, Ciudad de M\u00e9xico",
        "final_address": "09660\nCitlalli Ciudad de M\u00e9xico, CDMX, M\u00e9xico",
        "platform": "ubereats"
    },
    {
        "text": "Huaraches El Jarocho\nOferta superior \u2022 Ahorros exclusivos\nHuaraches El Jarocho\n4.5\n(140+)\n \u2022 \n16 min",
        "href": "https://www.ubereats.com/mx/store/huaraches-el-jarocho/rpVuzGDyWP-HstnEvt7l_g",
        "cate_source": "populares_cerca",
        "current_address": "09660, Ciudad de M\u00e9xico",
        "final_address": "09660\nCitlalli Ciudad de M\u00e9xico, CDMX, M\u00e9xico",
        "platform": "ubereats"
    },
    {
        "text": "La Barrita Sushi & Ramen\nOferta superior \u2022 2X1\nLa Barrita Sushi & Ramen\n4.7\n(1,000+)\n \u2022 \n40 min",
        "href": "https://www.ubereats.com/mx/store/la-barrita-sushi-%26-ramen-mexico-city/QO7TOXL9X06Hl4hzH6sQ_w",
        "cate_source": "populares_cerca",
        "current_address": "09660, Ciudad de M\u00e9xico",
        "final_address": "09660\nCitlalli Ciudad de M\u00e9xico, CDMX, M\u00e9xico",
        "platform": "ubereats"
    },
    {
        "text": "La Marisqueria\nLa Marisqueria\n4.5\n(120+)\n \u2022 \n17 min",
        "href": "https://www.ubereats.com/mx/store/la-marisqueria/ozZKuW-FSJqWAr6CB1oRjw",
        "cate_source": "populares_cerca",
        "current_address": "09660, Ciudad de M\u00e9xico",
        "final_address": "09660\nCitlalli Ciudad de M\u00e9xico, CDMX, M\u00e9xico",
        "platform": "ubereats"
    },
    {
        "text": "Marisquer\u00eda Las Brujas\nMarisquer\u00eda Las Brujas\n4.5\n(900+)\n \u2022 \n16 min",
        "href": "https://www.ubereats.com/mx/store/marisqueria-las-brujas/9CVF4qW4Rd6TCPdVzQmv9w",
        "cate_source": "populares_cerca",
        "current_address": "09660, Ciudad de M\u00e9xico",
        "final_address": "09660\nCitlalli Ciudad de M\u00e9xico, CDMX, M\u00e9xico",
        "platform": "ubereats"
    },
    {
        "text": "La Huella Del Drag\u00f3n\nOferta superior \u2022 2X1\nLa Huella Del Drag\u00f3n\n4.5\n(1,000+)\n \u2022 \n15 min",
        "href": "https://www.ubereats.com/mx/store/la-huella-del-dragon/p6B6sIVSS9i13KkhWpBXMQ",
        "cate_source": "populares_cerca",
        "current_address": "09660, Ciudad de M\u00e9xico",
        "final_address": "09660\nCitlalli Ciudad de M\u00e9xico, CDMX, M\u00e9xico",
        "platform": "ubereats"
    },
    {
        "text": "Adrenaline Wings\nAdrenaline Wings\n4.4\n(900+)\n \u2022 \n21 min",
        "href": "https://www.ubereats.com/mx/store/adrenaline-wings/KubA5ExrSAiCQGSRdpSxHQ",
        "cate_source": "populares_cerca",
        "current_address": "09660, Ciudad de M\u00e9xico",
        "final_address": "09660\nCitlalli Ciudad de M\u00e9xico, CDMX, M\u00e9xico",
        "platform": "ubereats"
    },
    {
        "text": "Lucky Sushi\nOferta superior \u2022 2X1\nLucky Sushi\n4.3\n(1,000+)\n \u2022 \n50 min",
        "href": "https://www.ubereats.com/mx/store/lucky-sushi-neza/WGHAMa6fWnWzJuWHa6Zu4g",
        "cate_source": "populares_cerca",
        "current_address": "09660, Ciudad de M\u00e9xico",
        "final_address": "09660\nCitlalli Ciudad de M\u00e9xico, CDMX, M\u00e9xico",
        "platform": "ubereats"
    },
    {
        "text": "El Peor de tus Antojos Snaks\nEl Peor de tus Antojos Snaks\n4.4\n(450+)\n \u2022 \n34 min",
        "href": "https://www.ubereats.com/mx/store/el-peor-de-tus-antojos-snaks/vNfVd3dNWRSQWSAoW4rwHQ",
        "cate_source": "populares_cerca",
        "current_address": "09660, Ciudad de M\u00e9xico",
        "final_address": "09660\nCitlalli Ciudad de M\u00e9xico, CDMX, M\u00e9xico",
        "platform": "ubereats"
    },
    {
        "text": "Hamburgueser\u00eda El Gran T-Bone\n2 Ofertas disponibles\nHamburgueser\u00eda El Gran T-Bone\n4.8\n(1,000+)\n \u2022 \n19 min",
        "href": "https://www.ubereats.com/mx/store/hamburgueseria-el-gran-t-bone/0DK_makNSba-U3AwiwMdEQ",
        "cate_source": "populares_cerca",
        "current_address": "09660, Ciudad de M\u00e9xico",
        "final_address": "09660\nCitlalli Ciudad de M\u00e9xico, CDMX, M\u00e9xico",
        "platform": "ubereats"
    },
    {
        "text": "Tortas Gigantes La No. 1\n2 Ofertas disponibles\nTortas Gigantes La No. 1\n4.5\n(1,000+)\n \u2022 \n29 min",
        "href": "https://www.ubereats.com/mx/store/tortas-gigantes-la-no-1/CT7nuD1LUQy6GO9WaSGbrw",
        "cate_source": "populares_cerca",
        "current_address": "09660, Ciudad de M\u00e9xico",
        "final_address": "09660\nCitlalli Ciudad de M\u00e9xico, CDMX, M\u00e9xico",
        "platform": "ubereats"
    },
    {
        "text": "La Parrilla Vikinga\nLa Parrilla Vikinga\n4.6\n(1,000+)\n \u2022 \n29 min",
        "href": "https://www.ubereats.com/mx/store/la-parrilla-vikinga/hFQVtyyRQ9e7mnO7whQbpQ",
        "cate_source": "populares_cerca",
        "current_address": "09660, Ciudad de M\u00e9xico",
        "final_address": "09660\nCitlalli Ciudad de M\u00e9xico, CDMX, M\u00e9xico",
        "platform": "ubereats"
    },
    {
        "text": "Super Tortas la Escondida\nOferta superior \u2022 Ahorros exclusivos\nSuper Tortas la Escondida\n4.5\n(410+)\n \u2022 \n35 min",
        "href": "https://www.ubereats.com/mx/store/super-tortas-la-escondida/d6ziE-JUWIuSROJ-GVryJw",
        "cate_source": "populares_cerca",
        "current_address": "09660, Ciudad de M\u00e9xico",
        "final_address": "09660\nCitlalli Ciudad de M\u00e9xico, CDMX, M\u00e9xico",
        "platform": "ubereats"
    },
    {
        "text": "AHHH CARBON\nAHHH CARBON\n4.4\n(84)\n \u2022 \n32 min",
        "href": "https://www.ubereats.com/mx/store/ahhh-carbon/w38k88bmTLaxZzKBk3NNVw",
        "cate_source": "populares_cerca",
        "current_address": "09660, Ciudad de M\u00e9xico",
        "final_address": "09660\nCitlalli Ciudad de M\u00e9xico, CDMX, M\u00e9xico",
        "platform": "ubereats"
    },
    {
        "text": "Burger & Joch's\nBurger & Joch's\n4.7\n(2,000+)\n \u2022 \n27 min",
        "href": "https://www.ubereats.com/mx/store/burger-%26-jochs-sur/bUSIFj4bR8exo_p4UvSfSQ",
        "cate_source": "populares_cerca",
        "current_address": "09660, Ciudad de M\u00e9xico",
        "final_address": "09660\nCitlalli Ciudad de M\u00e9xico, CDMX, M\u00e9xico",
        "platform": "ubereats"
    },
    {
        "text": "POLLINSKY\nPOLLINSKY\n4.7\n(70)\n \u2022 \n24 min",
        "href": "https://www.ubereats.com/mx/store/pollinsky-reyes/F-EQM8KrXJKI_MG2Rvy0Ig",
        "cate_source": "populares_cerca",
        "current_address": "09660, Ciudad de M\u00e9xico",
        "final_address": "09660\nCitlalli Ciudad de M\u00e9xico, CDMX, M\u00e9xico",
        "platform": "ubereats"
    },
    {
        "text": "Mi Bendito Caf\u00e9 Av. Texcoco\nAhorros exclusivos\nMi Bendito Caf\u00e9 Av. Texcoco\n4.5\n(410+)\n \u2022 \n29 min",
        "href": "https://www.ubereats.com/mx/store/mi-bendito-cafe-av-texcoco-mexico-city/wB4DE2wOX-6pYnlyivUtgA",
        "cate_source": "populares_cerca",
        "current_address": "09660, Ciudad de M\u00e9xico",
        "final_address": "09660\nCitlalli Ciudad de M\u00e9xico, CDMX, M\u00e9xico",
        "platform": "ubereats"
    },
    {
        "text": "Tacos Man\u00e1\nTacos Man\u00e1\n4.5\n(270+)\n \u2022 \n39 min",
        "href": "https://www.ubereats.com/mx/store/tacos-mana/YZz4DDoKW92HlFI0THHz8Q",
        "cate_source": "populares_cerca",
        "current_address": "09660, Ciudad de M\u00e9xico",
        "final_address": "09660\nCitlalli Ciudad de M\u00e9xico, CDMX, M\u00e9xico",
        "platform": "ubereats"
    },
    {
        "text": "Antojitos Mexicanos Vicky\nAntojitos Mexicanos Vicky\n4.6\n(2,000+)\n \u2022 \n23 min",
        "href": "https://www.ubereats.com/mx/store/antojitos-mexicanos-vicky/OMhkR0OBSs60fkhi8CD_Vg",
        "cate_source": "populares_cerca",
        "current_address": "09660, Ciudad de M\u00e9xico",
        "final_address": "09660\nCitlalli Ciudad de M\u00e9xico, CDMX, M\u00e9xico",
        "platform": "ubereats"
    },
    {
        "text": "Burgers Team.\n2 Ofertas disponibles\nBurgers Team.\n4.7\n(68)\n \u2022 \n24 min",
        "href": "https://www.ubereats.com/mx/store/burgers-team/-nUveFpUVKWhOpyXBw8kaQ",
        "cate_source": "populares_cerca",
        "current_address": "09660, Ciudad de M\u00e9xico",
        "final_address": "09660\nCitlalli Ciudad de M\u00e9xico, CDMX, M\u00e9xico",
        "platform": "ubereats"
    },
    {
        "text": "Sushi Miyaji y Algo Mas\n2 Ofertas disponibles\nSushi Miyaji y Algo Mas\n4.6\n(2,000+)\n \u2022 \n18 min",
        "href": "https://www.ubereats.com/mx/store/sushi-miyaji-y-algo-mas/NBu-e_GeQn6CxE7aQYmmSg",
        "cate_source": "populares_cerca",
        "current_address": "09660, Ciudad de M\u00e9xico",
        "final_address": "09660\nCitlalli Ciudad de M\u00e9xico, CDMX, M\u00e9xico",
        "platform": "ubereats"
    },
    {
        "text": "El Mexicano Restaurante y Cafeter\u00eda\nEl Mexicano Restaurante y Cafeter\u00eda\n4.4\n(360+)\n \u2022 \n29 min",
        "href": "https://www.ubereats.com/mx/store/el-mexicano-restaurante-y-cafeteria/vNZZTHmOS3GM3xk2cGFpeg",
        "cate_source": "populares_cerca",
        "current_address": "09660, Ciudad de M\u00e9xico",
        "final_address": "09660\nCitlalli Ciudad de M\u00e9xico, CDMX, M\u00e9xico",
        "platform": "ubereats"
    },
    {
        "text": "Donkey's Kitchen\n2 Ofertas disponibles\nDonkey's Kitchen\n4.7\n(5,000+)\n \u2022 \n50 min",
        "href": "https://www.ubereats.com/mx/store/donkeys-kitchen-av-mexico/VLEtaai6QUazreJ63LiPlQ",
        "cate_source": "populares_cerca",
        "current_address": "09660, Ciudad de M\u00e9xico",
        "final_address": "09660\nCitlalli Ciudad de M\u00e9xico, CDMX, M\u00e9xico",
        "platform": "ubereats"
    },
    {
        "text": "Taqueria y Parrilla los Cachorros\nTaqueria y Parrilla los Cachorros\n4.6\n(3,000+)\n \u2022 \n31 min",
        "href": "https://www.ubereats.com/mx/store/taqueria-y-parrilla-los-cachorros/E7JbxH7CQ5usonPw3500XQ",
        "cate_source": "populares_cerca",
        "current_address": "09660, Ciudad de M\u00e9xico",
        "final_address": "09660\nCitlalli Ciudad de M\u00e9xico, CDMX, M\u00e9xico",
        "platform": "ubereats"
    },
    {
        "text": "Crepas & Waffles Karamell\nCrepas & Waffles Karamell\n4.8\n(700+)\n \u2022 \n40 min",
        "href": "https://www.ubereats.com/mx/store/crepas-%26-waffles-karamell-santa-cruz/S92Gd_PdX5eYxA6DFcFpsg",
        "cate_source": "populares_cerca",
        "current_address": "09660, Ciudad de M\u00e9xico",
        "final_address": "09660\nCitlalli Ciudad de M\u00e9xico, CDMX, M\u00e9xico",
        "platform": "ubereats"
    },
    {
        "text": "Il Forno los Arcos\n3 Ofertas disponibles\nIl Forno los Arcos\n4.6\n(5,000+)\n \u2022 \n32 min",
        "href": "https://www.ubereats.com/mx/store/il-forno-los-arcos-aguilas/n8FzydxXRO2TczP6JMnnDA",
        "cate_source": "populares_cerca",
        "current_address": "09660, Ciudad de M\u00e9xico",
        "final_address": "09660\nCitlalli Ciudad de M\u00e9xico, CDMX, M\u00e9xico",
        "platform": "ubereats"
    },
    {
        "text": "Tortas Gigantes Sur 12 Matriz Agricola Oriental\nTortas Gigantes Sur 12 Matriz Agricola Oriental\n4.6\n(15,000+)\n \u2022 \n38 min",
        "href": "https://www.ubereats.com/mx/store/tortas-gigantes-sur-12-matriz-agricola-oriental/tnsuY1_pS9e3MkCNhI6EhQ",
        "cate_source": "populares_cerca",
        "current_address": "09660, Ciudad de M\u00e9xico",
        "final_address": "09660\nCitlalli Ciudad de M\u00e9xico, CDMX, M\u00e9xico",
        "platform": "ubereats"
    },
    {
        "text": "Aguas Con Las Tortas\n2 Ofertas disponibles\nAguas Con Las Tortas\n4.6\n(8,000+)\n \u2022 \n46 min",
        "href": "https://www.ubereats.com/mx/store/aguas-con-las-tortas/tzb5zw_NR3aoLINHhxj-PQ",
        "cate_source": "populares_cerca",
        "current_address": "09660, Ciudad de M\u00e9xico",
        "final_address": "09660\nCitlalli Ciudad de M\u00e9xico, CDMX, M\u00e9xico",
        "platform": "ubereats"
    },
    {
        "text": "TAQUERIAS KAIROS SAN LORENZO\n2X1\nTAQUERIAS KAIROS SAN LORENZO\n4.5\n(330+)\n \u2022 \n23 min",
        "href": "https://www.ubereats.com/mx/store/taquerias-kairos-san-lorenzo-iztapalapa/_siciQc6QTm9kZlWnrQR9Q",
        "cate_source": "populares_cerca",
        "current_address": "09660, Ciudad de M\u00e9xico",
        "final_address": "09660\nCitlalli Ciudad de M\u00e9xico, CDMX, M\u00e9xico",
        "platform": "ubereats"
    },
    {
        "text": "Casa de la costilla\nCasa de la costilla\n4.6\n(2,000+)\n \u2022 \n51 min",
        "href": "https://www.ubereats.com/mx/store/casa-de-la-costilla-agricola/sNVeXKJ3RB-uQplL-Llp_A",
        "cate_source": "populares_cerca",
        "current_address": "09660, Ciudad de M\u00e9xico",
        "final_address": "09660\nCitlalli Ciudad de M\u00e9xico, CDMX, M\u00e9xico",
        "platform": "ubereats"
    },
    {
        "text": "BIRRIERIA LA PERLA\nOferta superior \u2022 Ahorros exclusivos\nBIRRIERIA LA PERLA\n4.3\n(1,000+)\n \u2022 \n28 min",
        "href": "https://www.ubereats.com/mx/store/birrieria-la-perla-mexico-city/TOOcY6RwRk6vIWYqV5uEwA",
        "cate_source": "populares_cerca",
        "current_address": "09660, Ciudad de M\u00e9xico",
        "final_address": "09660\nCitlalli Ciudad de M\u00e9xico, CDMX, M\u00e9xico",
        "platform": "ubereats"
    },
    {
        "text": "El Camar\u00f3n Guasave\u00f1o\nEl Camar\u00f3n Guasave\u00f1o\n4.7\n(1,500+)\n \u2022 \n57 min",
        "href": "https://www.ubereats.com/mx/store/el-camaron-guasaveno-churubusco/VP-l6O-lQfGp6uLwW8EYZg",
        "cate_source": "populares_cerca",
        "current_address": "09660, Ciudad de M\u00e9xico",
        "final_address": "09660\nCitlalli Ciudad de M\u00e9xico, CDMX, M\u00e9xico",
        "platform": "ubereats"
    },
    {
        "text": "Birria House\nBirria House\n4.5\n(2,000+)\n \u2022 \n23 min",
        "href": "https://www.ubereats.com/mx/store/birria-house-leyes-de-reforma/kG46cAtxVtqxke2nXkIc9w",
        "cate_source": "populares_cerca",
        "current_address": "09660, Ciudad de M\u00e9xico",
        "final_address": "09660\nCitlalli Ciudad de M\u00e9xico, CDMX, M\u00e9xico",
        "platform": "ubereats"
    },
    {
        "text": "Sushi Sakura Oriente\nSushi Sakura Oriente\n4.8\n(46)\n \u2022 \n21 min",
        "href": "https://www.ubereats.com/mx/store/sushi-sakura-oriente/-OGUnLqZTQyPU68OSCmtHA",
        "cate_source": "populares_cerca",
        "current_address": "09660, Ciudad de M\u00e9xico",
        "final_address": "09660\nCitlalli Ciudad de M\u00e9xico, CDMX, M\u00e9xico",
        "platform": "ubereats"
    },
    {
        "text": "El Ma\u00edz Azteca\nEl Ma\u00edz Azteca\n4.1\n(6,000+)\n \u2022 \n35 min",
        "href": "https://www.ubereats.com/mx/store/el-maiz-azteca/II3tAyPIR2e-xMRrPnMn9Q",
        "cate_source": "populares_cerca",
        "current_address": "09660, Ciudad de M\u00e9xico",
        "final_address": "09660\nCitlalli Ciudad de M\u00e9xico, CDMX, M\u00e9xico",
        "platform": "ubereats"
    },
    {
        "text": "Pozoler\u00eda y Cenadur\u00eda Blanquis\nPozoler\u00eda y Cenadur\u00eda Blanquis\n4.6\n(20)\n \u2022 \n22 min",
        "href": "https://www.ubereats.com/mx/store/pozoleria-y-cenaduria-blanquis/ho55sHlOTo2CmXKR_U692w",
        "cate_source": "populares_cerca",
        "current_address": "09660, Ciudad de M\u00e9xico",
        "final_address": "09660\nCitlalli Ciudad de M\u00e9xico, CDMX, M\u00e9xico",
        "platform": "ubereats"
    },
    {
        "text": "LA COCINA DE LOS TIOS DEL RACHO\n4 Ofertas disponibles\nLA COCINA DE LOS TIOS DEL RACHO\n4.2\n(200+)\n \u2022 \n68 min",
        "href": "https://www.ubereats.com/mx/store/la-cocina-de-los-tios-del-racho-mexico-city/3It7kA_TTguf2sHtFyJbcA",
        "cate_source": "populares_cerca",
        "current_address": "09660, Ciudad de M\u00e9xico",
        "final_address": "09660\nCitlalli Ciudad de M\u00e9xico, CDMX, M\u00e9xico",
        "platform": "ubereats"
    },
    {
        "text": "Tacos Del Barrio San Lorenzo\nOferta superior \u2022 Ahorros exclusivos\nTacos Del Barrio San Lorenzo\n4.0\n(65)\n \u2022 \n38 min",
        "href": "https://www.ubereats.com/mx/store/tacos-del-barrio-san-lorenzo-mexico-city/8Zt-HK4GX02Hq7dbtRIp3Q",
        "cate_source": "populares_cerca",
        "current_address": "09660, Ciudad de M\u00e9xico",
        "final_address": "09660\nCitlalli Ciudad de M\u00e9xico, CDMX, M\u00e9xico",
        "platform": "ubereats"
    }
]