[
    {
        "text": "Mimi Sushi\nMimi Sushi\n5.0\n(22)\n \u2022 \n38 min",
        "href": "https://www.ubereats.com/mx/store/mimi-sushi-villa-milpa-alta-mexico-city/GS1ynqe1U--F-XDd8Va_iQ",
        "cate_source": "populares_cerca",
        "current_address": "12940, Ciudad de M\u00e9xico",
        "final_address": "12940\nCiudad de M\u00e9xico, M\u00e9xico",
        "platform": "ubereats"
    },
    {
        "text": "El Texcal\n2 Ofertas disponibles\nEl Texcal",
        "href": "https://www.ubereats.com/mx/store/el-texcal-fast-food/oLMWTOH7UfG3FbcghVSS6A",
        "cate_source": "populares_cerca",
        "current_address": "12940, Ciudad de M\u00e9xico",
        "final_address": "12940\nCiudad de M\u00e9xico, M\u00e9xico",
        "platform": "ubereats"
    },
    {
        "text": "Dulceria Luna\nGasta $149, ahorra $60\nDulceria Luna\n5.0\n(7)\n \u2022 \n23 min",
        "href": "https://www.ubereats.com/mx/store/dulceria-luna-mexico-city/dk0icsTYXRC_hIvE9NLKJQ",
        "cate_source": "populares_cerca",
        "current_address": "12940, Ciudad de M\u00e9xico",
        "final_address": "12940\nCiudad de M\u00e9xico, M\u00e9xico",
        "platform": "ubereats"
    }
]