[
    {
        "text": "Green Grass\n46 min\n\u00b7\n$ 46.90",
        "href": "https://www.rappi.com.mx/restaurantes/1306703853-green-grass",
        "cate_source": "populares_cerca",
        "current_address": "07188, Ciudad de M\u00e9xico",
        "final_address": "Sierra M\u00e9xico, Tlalpexco, 07188 Gustavo A Madero\nCDMX, M\u00e9xico",
        "platform": "rappi"
    },
    {
        "text": "KFC\n20 min\n\u00b7\n$ 30.90",
        "href": "https://www.rappi.com.mx/restaurantes/1923204142-kfc",
        "cate_source": "populares_cerca",
        "current_address": "07188, Ciudad de M\u00e9xico",
        "final_address": "Sierra M\u00e9xico, Tlalpexco, 07188 Gustavo A Madero\nCDMX, M\u00e9xico",
        "platform": "rappi"
    },
    {
        "text": "Sanborns\n46 min\n\u00b7\n$ 40.90",
        "href": "https://www.rappi.com.mx/restaurantes/1923221789-sanborns",
        "cate_source": "populares_cerca",
        "current_address": "07188, Ciudad de M\u00e9xico",
        "final_address": "Sierra M\u00e9xico, Tlalpexco, 07188 Gustavo A Madero\nCDMX, M\u00e9xico",
        "platform": "rappi"
    },
    {
        "text": "Donibuena\n30 min\n\u00b7\n$ 32.90",
        "href": "https://www.rappi.com.mx/restaurantes/1923251350-donibuena",
        "cate_source": "populares_cerca",
        "current_address": "07188, Ciudad de M\u00e9xico",
        "final_address": "Sierra M\u00e9xico, Tlalpexco, 07188 Gustavo A Madero\nCDMX, M\u00e9xico",
        "platform": "rappi"
    },
    {
        "text": "Helados Holanda.\n35 min\n\u00b7\n$ 28.90",
        "href": "https://www.rappi.com.mx/restaurantes/1923301663-helados-holanda",
        "cate_source": "populares_cerca",
        "current_address": "07188, Ciudad de M\u00e9xico",
        "final_address": "Sierra M\u00e9xico, Tlalpexco, 07188 Gustavo A Madero\nCDMX, M\u00e9xico",
        "platform": "rappi"
    },
    {
        "text": "Little Caesars\n46 min\n\u00b7\n$ 36.90",
        "href": "https://www.rappi.com.mx/restaurantes/1923423912-little-caesars",
        "cate_source": "populares_cerca",
        "current_address": "07188, Ciudad de M\u00e9xico",
        "final_address": "Sierra M\u00e9xico, Tlalpexco, 07188 Gustavo A Madero\nCDMX, M\u00e9xico",
        "platform": "rappi"
    },
    {
        "text": "Los Chenchos Carnitas\n45 min\n\u00b7\n$ 44.90",
        "href": "https://www.rappi.com.mx/restaurantes/1923460653-los-chenchos-carnitas",
        "cate_source": "populares_cerca",
        "current_address": "07188, Ciudad de M\u00e9xico",
        "final_address": "Sierra M\u00e9xico, Tlalpexco, 07188 Gustavo A Madero\nCDMX, M\u00e9xico",
        "platform": "rappi"
    },
    {
        "text": "Tako Tote\n20 min\n\u00b7\n$ 44.90",
        "href": "https://www.rappi.com.mx/restaurantes/1923699203-tako-tote",
        "cate_source": "populares_cerca",
        "current_address": "07188, Ciudad de M\u00e9xico",
        "final_address": "Sierra M\u00e9xico, Tlalpexco, 07188 Gustavo A Madero\nCDMX, M\u00e9xico",
        "platform": "rappi"
    },
    {
        "text": "Pan y Reposter\u00eda Fina Ochoa\n25 min\n\u00b7\n$ 36.90",
        "href": "https://www.rappi.com.mx/restaurantes/1923701994-pan-y-reposteria-fina-ochoa",
        "cate_source": "populares_cerca",
        "current_address": "07188, Ciudad de M\u00e9xico",
        "final_address": "Sierra M\u00e9xico, Tlalpexco, 07188 Gustavo A Madero\nCDMX, M\u00e9xico",
        "platform": "rappi"
    },
    {
        "text": "La Venus de Jalea\n40 min\n\u00b7\n$ 40.90",
        "href": "https://www.rappi.com.mx/restaurantes/1923761719-la-venus-de-jalea",
        "cate_source": "populares_cerca",
        "current_address": "07188, Ciudad de M\u00e9xico",
        "final_address": "Sierra M\u00e9xico, Tlalpexco, 07188 Gustavo A Madero\nCDMX, M\u00e9xico",
        "platform": "rappi"
    },
    {
        "text": "El Ma\u00f1anero \u00a1desayuna Delicioso!\n46 min\n\u00b7\n$ 32.90",
        "href": "https://www.rappi.com.mx/restaurantes/1923779874-el-mananero-desayuna-delicioso",
        "cate_source": "populares_cerca",
        "current_address": "07188, Ciudad de M\u00e9xico",
        "final_address": "Sierra M\u00e9xico, Tlalpexco, 07188 Gustavo A Madero\nCDMX, M\u00e9xico",
        "platform": "rappi"
    },
    {
        "text": "Burger King\n30 min\n\u00b7\n$ 36.90",
        "href": "https://www.rappi.com.mx/restaurantes/1923791400-burger-king",
        "cate_source": "populares_cerca",
        "current_address": "07188, Ciudad de M\u00e9xico",
        "final_address": "Sierra M\u00e9xico, Tlalpexco, 07188 Gustavo A Madero\nCDMX, M\u00e9xico",
        "platform": "rappi"
    },
    {
        "text": "Toks\n30 min\n\u00b7\n$ 28.90",
        "href": "https://www.rappi.com.mx/restaurantes/1923798252-toks",
        "cate_source": "populares_cerca",
        "current_address": "07188, Ciudad de M\u00e9xico",
        "final_address": "Sierra M\u00e9xico, Tlalpexco, 07188 Gustavo A Madero\nCDMX, M\u00e9xico",
        "platform": "rappi"
    },
    {
        "text": "Carnitas Don Pepe...\n20 min\n\u00b7\n$ 20.90",
        "href": "https://www.rappi.com.mx/restaurantes/1930015485-carnitas-don-pepe",
        "cate_source": "populares_cerca",
        "current_address": "07188, Ciudad de M\u00e9xico",
        "final_address": "Sierra M\u00e9xico, Tlalpexco, 07188 Gustavo A Madero\nCDMX, M\u00e9xico",
        "platform": "rappi"
    },
    {
        "text": "Taqueria el Tigre To\u00f1o Suc Arbolitos\n35 min\n\u00b7\n$ 24.90",
        "href": "https://www.rappi.com.mx/restaurantes/1930040170-taqueria-el-tigre-tono-suc-arbolito",
        "cate_source": "populares_cerca",
        "current_address": "07188, Ciudad de M\u00e9xico",
        "final_address": "Sierra M\u00e9xico, Tlalpexco, 07188 Gustavo A Madero\nCDMX, M\u00e9xico",
        "platform": "rappi"
    },
    {
        "text": "Lecaroz\n25 min\n\u00b7\n$ 32.90",
        "href": "https://www.rappi.com.mx/restaurantes/1930046753-lecaroz",
        "cate_source": "populares_cerca",
        "current_address": "07188, Ciudad de M\u00e9xico",
        "final_address": "Sierra M\u00e9xico, Tlalpexco, 07188 Gustavo A Madero\nCDMX, M\u00e9xico",
        "platform": "rappi"
    },
    {
        "text": "Fuente de Sodas Roxx\n25 min\n\u00b7\n$ 36.90",
        "href": "https://www.rappi.com.mx/restaurantes/1930085914-fuente-de-sodas-roxx",
        "cate_source": "populares_cerca",
        "current_address": "07188, Ciudad de M\u00e9xico",
        "final_address": "Sierra M\u00e9xico, Tlalpexco, 07188 Gustavo A Madero\nCDMX, M\u00e9xico",
        "platform": "rappi"
    },
    {
        "text": "Expendio Roxcar\n25 min\n\u00b7\n$ 36.90",
        "href": "https://www.rappi.com.mx/restaurantes/1930088575-expendio-roxcar",
        "cate_source": "populares_cerca",
        "current_address": "07188, Ciudad de M\u00e9xico",
        "final_address": "Sierra M\u00e9xico, Tlalpexco, 07188 Gustavo A Madero\nCDMX, M\u00e9xico",
        "platform": "rappi"
    },
    {
        "text": "Antojitos Maru5\n25 min\n\u00b7\n$ 24.90",
        "href": "https://www.rappi.com.mx/restaurantes/1930101470-antojitos-maru5",
        "cate_source": "populares_cerca",
        "current_address": "07188, Ciudad de M\u00e9xico",
        "final_address": "Sierra M\u00e9xico, Tlalpexco, 07188 Gustavo A Madero\nCDMX, M\u00e9xico",
        "platform": "rappi"
    },
    {
        "text": "Marisquer\u00eda La Bamba\n35 min\n\u00b7\n$ 40.90",
        "href": "https://www.rappi.com.mx/restaurantes/1930112854-marisqueria-la-bamba",
        "cate_source": "populares_cerca",
        "current_address": "07188, Ciudad de M\u00e9xico",
        "final_address": "Sierra M\u00e9xico, Tlalpexco, 07188 Gustavo A Madero\nCDMX, M\u00e9xico",
        "platform": "rappi"
    }
]