[
    {
        "text": "Port\u00f3n Maya\n29 min\n\u00b7\n$ 44.90",
        "href": "https://www.rappi.com.mx/restaurantes/10000449-porton-maya",
        "cate_source": "populares_cerca",
        "current_address": "08770, Ciudad de M\u00e9xico",
        "final_address": "08770, Los Picos de Iztacalco Secci\u00f3n 1A, Iztacalco\nCDMX, M\u00e9xico",
        "platform": "rappi"
    },
    {
        "text": "Pinche Gringo BBQ\n24 min\n\u00b7\n$ 20.90",
        "href": "https://www.rappi.com.mx/restaurantes/900001475-pinche-gringo-bbq",
        "cate_source": "populares_cerca",
        "current_address": "08770, Ciudad de M\u00e9xico",
        "final_address": "08770, Los Picos de Iztacalco Secci\u00f3n 1A, Iztacalco\nCDMX, M\u00e9xico",
        "platform": "rappi"
    },
    {
        "text": "Pizzalianni's Express\n29 min\n\u00b7\n$ 38.90",
        "href": "https://www.rappi.com.mx/restaurantes/990002499-pizzaliannis-express",
        "cate_source": "populares_cerca",
        "current_address": "08770, Ciudad de M\u00e9xico",
        "final_address": "08770, Los Picos de Iztacalco Secci\u00f3n 1A, Iztacalco\nCDMX, M\u00e9xico",
        "platform": "rappi"
    },
    {
        "text": "Paparruls Burger\n45 min\n\u00b7\n$ 36.90",
        "href": "https://www.rappi.com.mx/restaurantes/990002957-paparruls-burger",
        "cate_source": "populares_cerca",
        "current_address": "08770, Ciudad de M\u00e9xico",
        "final_address": "08770, Los Picos de Iztacalco Secci\u00f3n 1A, Iztacalco\nCDMX, M\u00e9xico",
        "platform": "rappi"
    },
    {
        "text": "Kukulkan\n34 min\n\u00b7\n$ 34.90",
        "href": "https://www.rappi.com.mx/restaurantes/990002966-kukulkan",
        "cate_source": "populares_cerca",
        "current_address": "08770, Ciudad de M\u00e9xico",
        "final_address": "08770, Los Picos de Iztacalco Secci\u00f3n 1A, Iztacalco\nCDMX, M\u00e9xico",
        "platform": "rappi"
    },
    {
        "text": "Magic Prime\n24 min\n\u00b7\n$ 46.90",
        "href": "https://www.rappi.com.mx/restaurantes/990005182-magic-prime",
        "cate_source": "populares_cerca",
        "current_address": "08770, Ciudad de M\u00e9xico",
        "final_address": "08770, Los Picos de Iztacalco Secci\u00f3n 1A, Iztacalco\nCDMX, M\u00e9xico",
        "platform": "rappi"
    },
    {
        "text": "Tim Hortons\n19 min\n\u00b7\n$ 24.90",
        "href": "https://www.rappi.com.mx/restaurantes/1930281382-tim-hortons",
        "cate_source": "populares_cerca",
        "current_address": "08770, Ciudad de M\u00e9xico",
        "final_address": "08770, Los Picos de Iztacalco Secci\u00f3n 1A, Iztacalco\nCDMX, M\u00e9xico",
        "platform": "rappi"
    },
    {
        "text": "Papa John's\n39 min\n\u00b7\n$ 36.90",
        "href": "https://www.rappi.com.mx/restaurantes/990005884-papa-johns",
        "cate_source": "populares_cerca",
        "current_address": "08770, Ciudad de M\u00e9xico",
        "final_address": "08770, Los Picos de Iztacalco Secci\u00f3n 1A, Iztacalco\nCDMX, M\u00e9xico",
        "platform": "rappi"
    },
    {
        "text": "Pozole El Chato\n39 min\n\u00b7\n$ 34.90",
        "href": "https://www.rappi.com.mx/restaurantes/990006445-pozole-el-chato",
        "cate_source": "populares_cerca",
        "current_address": "08770, Ciudad de M\u00e9xico",
        "final_address": "08770, Los Picos de Iztacalco Secci\u00f3n 1A, Iztacalco\nCDMX, M\u00e9xico",
        "platform": "rappi"
    },
    {
        "text": "The Cheesecake Factory\n45 min\n\u00b7\n$ 38.90",
        "href": "https://www.rappi.com.mx/restaurantes/990006900-the-cheesecake-factory",
        "cate_source": "populares_cerca",
        "current_address": "08770, Ciudad de M\u00e9xico",
        "final_address": "08770, Los Picos de Iztacalco Secci\u00f3n 1A, Iztacalco\nCDMX, M\u00e9xico",
        "platform": "rappi"
    },
    {
        "text": "Delisiu\n45 min\n\u00b7\n$ 36.90",
        "href": "https://www.rappi.com.mx/restaurantes/990008628-delisiu",
        "cate_source": "populares_cerca",
        "current_address": "08770, Ciudad de M\u00e9xico",
        "final_address": "08770, Los Picos de Iztacalco Secci\u00f3n 1A, Iztacalco\nCDMX, M\u00e9xico",
        "platform": "rappi"
    },
    {
        "text": "El Pez Muy Muy\n24 min\n\u00b7\n$ 44.90",
        "href": "https://www.rappi.com.mx/restaurantes/1306701056-el-pez-muy-muy",
        "cate_source": "populares_cerca",
        "current_address": "08770, Ciudad de M\u00e9xico",
        "final_address": "08770, Los Picos de Iztacalco Secci\u00f3n 1A, Iztacalco\nCDMX, M\u00e9xico",
        "platform": "rappi"
    },
    {
        "text": "Taco Naco\n29 min\n\u00b7\n$ 34.90",
        "href": "https://www.rappi.com.mx/restaurantes/1306701350-taco-naco",
        "cate_source": "populares_cerca",
        "current_address": "08770, Ciudad de M\u00e9xico",
        "final_address": "08770, Los Picos de Iztacalco Secci\u00f3n 1A, Iztacalco\nCDMX, M\u00e9xico",
        "platform": "rappi"
    },
    {
        "text": "El Baj\u00edo\n39 min\n\u00b7\n$ 36.90",
        "href": "https://www.rappi.com.mx/restaurantes/1306702178-el-bajio",
        "cate_source": "populares_cerca",
        "current_address": "08770, Ciudad de M\u00e9xico",
        "final_address": "08770, Los Picos de Iztacalco Secci\u00f3n 1A, Iztacalco\nCDMX, M\u00e9xico",
        "platform": "rappi"
    },
    {
        "text": "Moshi Moshi\n45 min\n\u00b7\n$ 38.90",
        "href": "https://www.rappi.com.mx/restaurantes/1306702207-moshi-moshi",
        "cate_source": "populares_cerca",
        "current_address": "08770, Ciudad de M\u00e9xico",
        "final_address": "08770, Los Picos de Iztacalco Secci\u00f3n 1A, Iztacalco\nCDMX, M\u00e9xico",
        "platform": "rappi"
    },
    {
        "text": "Chilaquilito\n29 min\n\u00b7\n$ 30.90",
        "href": "https://www.rappi.com.mx/restaurantes/1306703419-chilaquilito",
        "cate_source": "populares_cerca",
        "current_address": "08770, Ciudad de M\u00e9xico",
        "final_address": "08770, Los Picos de Iztacalco Secci\u00f3n 1A, Iztacalco\nCDMX, M\u00e9xico",
        "platform": "rappi"
    },
    {
        "text": "Moyo\n35 min\n\u00b7\n$ 28.90",
        "href": "https://www.rappi.com.mx/restaurantes/1306703521-moyo",
        "cate_source": "populares_cerca",
        "current_address": "08770, Ciudad de M\u00e9xico",
        "final_address": "08770, Los Picos de Iztacalco Secci\u00f3n 1A, Iztacalco\nCDMX, M\u00e9xico",
        "platform": "rappi"
    },
    {
        "text": "El Pap\u00e1 de los Naranjitos\n29 min\n\u00b7\n$ 36.90",
        "href": "https://www.rappi.com.mx/restaurantes/1306703943-el-papa-de-los-naranjitos",
        "cate_source": "populares_cerca",
        "current_address": "08770, Ciudad de M\u00e9xico",
        "final_address": "08770, Los Picos de Iztacalco Secci\u00f3n 1A, Iztacalco\nCDMX, M\u00e9xico",
        "platform": "rappi"
    },
    {
        "text": "Kikiripizza\n34 min\n\u00b7\n$ 28.90",
        "href": "https://www.rappi.com.mx/restaurantes/1306704741-kikiripizza",
        "cate_source": "populares_cerca",
        "current_address": "08770, Ciudad de M\u00e9xico",
        "final_address": "08770, Los Picos de Iztacalco Secci\u00f3n 1A, Iztacalco\nCDMX, M\u00e9xico",
        "platform": "rappi"
    },
    {
        "text": "Rebel Wings\n24 min\n\u00b7\n$ 18.90",
        "href": "https://www.rappi.com.mx/restaurantes/1306705538-rebel-wings",
        "cate_source": "populares_cerca",
        "current_address": "08770, Ciudad de M\u00e9xico",
        "final_address": "08770, Los Picos de Iztacalco Secci\u00f3n 1A, Iztacalco\nCDMX, M\u00e9xico",
        "platform": "rappi"
    }
]