[
    {
        "text": "Green Grass\n46 min\n\u00b7\n$ 42.90",
        "href": "https://www.rappi.com.mx/restaurantes/1306717001-green-grass",
        "cate_source": "populares_cerca",
        "current_address": "13545, Ciudad de M\u00e9xico",
        "final_address": "13545, Ampliaci\u00f3n La Conchita, Tl\u00e1huac\nCDMX, M\u00e9xico",
        "platform": "rappi"
    },
    {
        "text": "Lecaroz\n30 min\n\u00b7\n$ 42.90",
        "href": "https://www.rappi.com.mx/restaurantes/1923291567-lecaroz",
        "cate_source": "populares_cerca",
        "current_address": "13545, Ciudad de M\u00e9xico",
        "final_address": "13545, Ampliaci\u00f3n La Conchita, Tl\u00e1huac\nCDMX, M\u00e9xico",
        "platform": "rappi"
    },
    {
        "text": "McDonald's\n30 min\n\u00b7\n$ 34.90",
        "href": "https://www.rappi.com.mx/restaurantes/1923804208-mcdonalds",
        "cate_source": "populares_cerca",
        "current_address": "13545, Ciudad de M\u00e9xico",
        "final_address": "13545, Ampliaci\u00f3n La Conchita, Tl\u00e1huac\nCDMX, M\u00e9xico",
        "platform": "rappi"
    },
    {
        "text": "Starbucks\n15 min\n\u00b7\n$ 22.90",
        "href": "https://www.rappi.com.mx/restaurantes/1930005248-starbucks",
        "cate_source": "populares_cerca",
        "current_address": "13545, Ciudad de M\u00e9xico",
        "final_address": "13545, Ampliaci\u00f3n La Conchita, Tl\u00e1huac\nCDMX, M\u00e9xico",
        "platform": "rappi"
    },
    {
        "text": "Desayunos y m\u00e1s\n40 min\n\u00b7\n$ 28.90",
        "href": "https://www.rappi.com.mx/restaurantes/1930008640-desayunos-y-mas",
        "cate_source": "populares_cerca",
        "current_address": "13545, Ciudad de M\u00e9xico",
        "final_address": "13545, Ampliaci\u00f3n La Conchita, Tl\u00e1huac\nCDMX, M\u00e9xico",
        "platform": "rappi"
    },
    {
        "text": "Vips\n46 min\n\u00b7\n$ 38.90",
        "href": "https://www.rappi.com.mx/restaurantes/1930011574-vips",
        "cate_source": "populares_cerca",
        "current_address": "13545, Ciudad de M\u00e9xico",
        "final_address": "13545, Ampliaci\u00f3n La Conchita, Tl\u00e1huac\nCDMX, M\u00e9xico",
        "platform": "rappi"
    },
    {
        "text": "Mariscos Marnhez\n20 min\n\u00b7\n$ 16.90",
        "href": "https://www.rappi.com.mx/restaurantes/1930042558-mariscos-marnhez",
        "cate_source": "populares_cerca",
        "current_address": "13545, Ciudad de M\u00e9xico",
        "final_address": "13545, Ampliaci\u00f3n La Conchita, Tl\u00e1huac\nCDMX, M\u00e9xico",
        "platform": "rappi"
    },
    {
        "text": "Sushi Simo\n25 min\n\u00b7\n$ 28.90",
        "href": "https://www.rappi.com.mx/restaurantes/1930045889-sushi-simo",
        "cate_source": "populares_cerca",
        "current_address": "13545, Ciudad de M\u00e9xico",
        "final_address": "13545, Ampliaci\u00f3n La Conchita, Tl\u00e1huac\nCDMX, M\u00e9xico",
        "platform": "rappi"
    },
    {
        "text": "El Buey Loco\n12 min\n\u00b7\n$ 10.90",
        "href": "https://www.rappi.com.mx/restaurantes/1930047459-el-buey-loco",
        "cate_source": "populares_cerca",
        "current_address": "13545, Ciudad de M\u00e9xico",
        "final_address": "13545, Ampliaci\u00f3n La Conchita, Tl\u00e1huac\nCDMX, M\u00e9xico",
        "platform": "rappi"
    },
    {
        "text": "Pasteler\u00edas Esperanza\n20 min\n\u00b7\n$ 10.90",
        "href": "https://www.rappi.com.mx/restaurantes/1930067293-pastelerias-esperanza",
        "cate_source": "populares_cerca",
        "current_address": "13545, Ciudad de M\u00e9xico",
        "final_address": "13545, Ampliaci\u00f3n La Conchita, Tl\u00e1huac\nCDMX, M\u00e9xico",
        "platform": "rappi"
    },
    {
        "text": "Dr Chilaquil Milagroso\n15 min\n\u00b7\n$ 18.90",
        "href": "https://www.rappi.com.mx/restaurantes/1930070569-dr-chilaquil-milagroso",
        "cate_source": "populares_cerca",
        "current_address": "13545, Ciudad de M\u00e9xico",
        "final_address": "13545, Ampliaci\u00f3n La Conchita, Tl\u00e1huac\nCDMX, M\u00e9xico",
        "platform": "rappi"
    },
    {
        "text": "Berakhah Pozole y Mas\n46 min\n\u00b7\n$ 32.90",
        "href": "https://www.rappi.com.mx/restaurantes/1930085937-berakhah-pozole-y-mas",
        "cate_source": "populares_cerca",
        "current_address": "13545, Ciudad de M\u00e9xico",
        "final_address": "13545, Ampliaci\u00f3n La Conchita, Tl\u00e1huac\nCDMX, M\u00e9xico",
        "platform": "rappi"
    },
    {
        "text": "Fitfood Vitalidad a tu Puerta\n15 min\n\u00b7\n$ 34.90",
        "href": "https://www.rappi.com.mx/restaurantes/1930108383-fitfood-vitalidad-a-tu-puerta",
        "cate_source": "populares_cerca",
        "current_address": "13545, Ciudad de M\u00e9xico",
        "final_address": "13545, Ampliaci\u00f3n La Conchita, Tl\u00e1huac\nCDMX, M\u00e9xico",
        "platform": "rappi"
    },
    {
        "text": "Empanadas Veracruzanas\n20 min\n\u00b7\n$ 32.90",
        "href": "https://www.rappi.com.mx/restaurantes/1930269120-empanadas-veracruzanas",
        "cate_source": "populares_cerca",
        "current_address": "13545, Ciudad de M\u00e9xico",
        "final_address": "13545, Ampliaci\u00f3n La Conchita, Tl\u00e1huac\nCDMX, M\u00e9xico",
        "platform": "rappi"
    },
    {
        "text": "Food Truck Birria la Jardinera\n12 min\n\u00b7\n$ 16.90",
        "href": "https://www.rappi.com.mx/restaurantes/1930272892-food-truck-birria-la-jardinera",
        "cate_source": "populares_cerca",
        "current_address": "13545, Ciudad de M\u00e9xico",
        "final_address": "13545, Ampliaci\u00f3n La Conchita, Tl\u00e1huac\nCDMX, M\u00e9xico",
        "platform": "rappi"
    },
    {
        "text": "Tortilleria Mi Morenita\n15 min\n\u00b7\n$ 48.90",
        "href": "https://www.rappi.com.mx/restaurantes/1930288365-tortilleria-mi-morenita",
        "cate_source": "populares_cerca",
        "current_address": "13545, Ciudad de M\u00e9xico",
        "final_address": "13545, Ampliaci\u00f3n La Conchita, Tl\u00e1huac\nCDMX, M\u00e9xico",
        "platform": "rappi"
    },
    {
        "text": "Coffee Olivos\n25 min\n\u00b7\n$ 40.90",
        "href": "https://www.rappi.com.mx/restaurantes/1930290838-coffee-olivos",
        "cate_source": "populares_cerca",
        "current_address": "13545, Ciudad de M\u00e9xico",
        "final_address": "13545, Ampliaci\u00f3n La Conchita, Tl\u00e1huac\nCDMX, M\u00e9xico",
        "platform": "rappi"
    },
    {
        "text": "Sushi Jim & Jos\n46 min\n\u00b7\n$ 44.90",
        "href": "https://www.rappi.com.mx/restaurantes/1930316585-sushi-jim-y-jos",
        "cate_source": "populares_cerca",
        "current_address": "13545, Ciudad de M\u00e9xico",
        "final_address": "13545, Ampliaci\u00f3n La Conchita, Tl\u00e1huac\nCDMX, M\u00e9xico",
        "platform": "rappi"
    },
    {
        "text": "Pollo Frito Fenix\n25 min\n\u00b7\n$ 40.90",
        "href": "https://www.rappi.com.mx/restaurantes/1930330435-pollo-frito-fenix",
        "cate_source": "populares_cerca",
        "current_address": "13545, Ciudad de M\u00e9xico",
        "final_address": "13545, Ampliaci\u00f3n La Conchita, Tl\u00e1huac\nCDMX, M\u00e9xico",
        "platform": "rappi"
    },
    {
        "text": "Cinemex\n35 min\n\u00b7\n$ 28.90",
        "href": "https://www.rappi.com.mx/restaurantes/1923248899-cinemex",
        "cate_source": "populares_cerca",
        "current_address": "13545, Ciudad de M\u00e9xico",
        "final_address": "13545, Ampliaci\u00f3n La Conchita, Tl\u00e1huac\nCDMX, M\u00e9xico",
        "platform": "rappi"
    }
]