[
    {
        "text": "Pizza Maestra Lindavista\nOferta superior \u2022 Ahorros exclusivos\nPizza Maestra Lindavista\n4.4\n(2,000+)\n \u2022 \n45 min",
        "href": "https://www.ubereats.com/mx/store/pizza-maestra-lindavista/eTw-6c8JXGCM9fHoaCvkYQ",
        "cate_source": "populares_cerca",
        "current_address": "07310, Ciudad de M\u00e9xico",
        "final_address": "Location marker\n07310\nCandelaria Ticoman Ciudad de M\u00e9xico, CDMX, M\u00e9xico",
        "platform": "ubereats"
    },
    {
        "text": "Alitas Maestras Lindavista\nOferta superior \u2022 Ahorros exclusivos\nAlitas Maestras Lindavista\n4.3\n(1,000+)\n \u2022 \n45 min",
        "href": "https://www.ubereats.com/mx/store/alitas-maestras-lindavista/1OCIOJtnWfOXf3vQ5NCP3Q",
        "cate_source": "populares_cerca",
        "current_address": "07310, Ciudad de M\u00e9xico",
        "final_address": "Location marker\n07310\nCandelaria Ticoman Ciudad de M\u00e9xico, CDMX, M\u00e9xico",
        "platform": "ubereats"
    },
    {
        "text": "La barrica wings\nOferta superior \u2022 3 Ofertas disponibles\nLa barrica wings\n4.5\n(900+)\n \u2022 \n50 min",
        "href": "https://www.ubereats.com/mx/store/la-barrica-wings/pchcF1_zSeWeArJzpCuY1w",
        "cate_source": "populares_cerca",
        "current_address": "07310, Ciudad de M\u00e9xico",
        "final_address": "Location marker\n07310\nCandelaria Ticoman Ciudad de M\u00e9xico, CDMX, M\u00e9xico",
        "platform": "ubereats"
    },
    {
        "text": "Caf\u00e9 Ka\u00b4Loc Atana Lindavista\nCosto de env\u00edo de $0 (gasto de $100)\nCaf\u00e9 Ka\u00b4Loc Atana Lindavista\n4.8\n(310+)\n \u2022 \n30 min",
        "href": "https://www.ubereats.com/mx/store/cafe-ka-loc-atana-lindavista/HCdrmw62WoWG6kSpRH8z7w",
        "cate_source": "populares_cerca",
        "current_address": "07310, Ciudad de M\u00e9xico",
        "final_address": "Location marker\n07310\nCandelaria Ticoman Ciudad de M\u00e9xico, CDMX, M\u00e9xico",
        "platform": "ubereats"
    },
    {
        "text": "Tortas \"El Tio\"\nTortas \"El Tio\"\n4.7\n(4,000+)\n \u2022 \n35 min",
        "href": "https://www.ubereats.com/mx/store/tortas-%22el-tio%22/mmS0tENtRKeZXU2utBe1Vw",
        "cate_source": "populares_cerca",
        "current_address": "07310, Ciudad de M\u00e9xico",
        "final_address": "Location marker\n07310\nCandelaria Ticoman Ciudad de M\u00e9xico, CDMX, M\u00e9xico",
        "platform": "ubereats"
    },
    {
        "text": "Taqueria \" la mula de seises\"\nTaqueria \" la mula de seises\"\n4.5\n(700+)\n \u2022 \n35 min",
        "href": "https://www.ubereats.com/mx/store/taqueria-%22-la-mula-de-seises%22/Z_NCbrEiRR-yqWu_Gl1VKA",
        "cate_source": "populares_cerca",
        "current_address": "07310, Ciudad de M\u00e9xico",
        "final_address": "Location marker\n07310\nCandelaria Ticoman Ciudad de M\u00e9xico, CDMX, M\u00e9xico",
        "platform": "ubereats"
    },
    {
        "text": "Quesadillas Mari Fortuna\nGasta $300, ahorra $120\nQuesadillas Mari Fortuna\n4.5\n(4,000+)\n \u2022 \n50 min",
        "href": "https://www.ubereats.com/mx/store/quesadillas-mari-fortuna/QaQcuFWSXpqm2xi-t4iiZw",
        "cate_source": "populares_cerca",
        "current_address": "07310, Ciudad de M\u00e9xico",
        "final_address": "Location marker\n07310\nCandelaria Ticoman Ciudad de M\u00e9xico, CDMX, M\u00e9xico",
        "platform": "ubereats"
    },
    {
        "text": "Sixties Burger Vista Norte\nOferta superior \u2022 Ahorros exclusivos\nSixties Burger Vista Norte\n4.0\n(83)\n \u2022 \n40 min",
        "href": "https://www.ubereats.com/mx/store/sixties-burger-vista-norte-mexico-city/n5J-d1eMQWGC5pOuh593YA",
        "cate_source": "populares_cerca",
        "current_address": "07310, Ciudad de M\u00e9xico",
        "final_address": "Location marker\n07310\nCandelaria Ticoman Ciudad de M\u00e9xico, CDMX, M\u00e9xico",
        "platform": "ubereats"
    },
    {
        "text": "Gema Sushi\nGema Sushi\n4.8\n(1,500+)\n \u2022 \n40 min",
        "href": "https://www.ubereats.com/mx/store/gema-sushi/OXbjqLlrQDOCM54lruIZPg",
        "cate_source": "populares_cerca",
        "current_address": "07310, Ciudad de M\u00e9xico",
        "final_address": "Location marker\n07310\nCandelaria Ticoman Ciudad de M\u00e9xico, CDMX, M\u00e9xico",
        "platform": "ubereats"
    },
    {
        "text": "Cassava Roots Parque Lindavista\nCassava Roots Parque Lindavista\n4.8\n(380+)\n \u2022 \n40 min",
        "href": "https://www.ubereats.com/mx/store/cassava-roots-parque-lindavista/hSFUCpBWXLm5tHPq3w8Gsg",
        "cate_source": "populares_cerca",
        "current_address": "07310, Ciudad de M\u00e9xico",
        "final_address": "Location marker\n07310\nCandelaria Ticoman Ciudad de M\u00e9xico, CDMX, M\u00e9xico",
        "platform": "ubereats"
    },
    {
        "text": "La Venus de Jalea\n2 Ofertas disponibles\nLa Venus de Jalea\n4.6\n(310+)\n \u2022 \n40 min",
        "href": "https://www.ubereats.com/mx/store/la-venus-de-jalea/RMsHpWcVQZipXDnTta0AiQ",
        "cate_source": "populares_cerca",
        "current_address": "07310, Ciudad de M\u00e9xico",
        "final_address": "Location marker\n07310\nCandelaria Ticoman Ciudad de M\u00e9xico, CDMX, M\u00e9xico",
        "platform": "ubereats"
    },
    {
        "text": "La Michoacana de Sierravista\nLa Michoacana de Sierravista\n4.9\n(2,000+)\n \u2022 \n30 min",
        "href": "https://www.ubereats.com/mx/store/la-michoacana-de-sierravista/qHiWKKorTh-TUpNb7Rz9jg",
        "cate_source": "populares_cerca",
        "current_address": "07310, Ciudad de M\u00e9xico",
        "final_address": "Location marker\n07310\nCandelaria Ticoman Ciudad de M\u00e9xico, CDMX, M\u00e9xico",
        "platform": "ubereats"
    },
    {
        "text": "Busher Cocdril's Acueducto\nBusher Cocdril's Acueducto\n4.3\n(210+)\n \u2022 \n25 min",
        "href": "https://www.ubereats.com/mx/store/busher-cocdrils-acueducto/y3Pw8YdLQD2_0BQs8vxVVw",
        "cate_source": "populares_cerca",
        "current_address": "07310, Ciudad de M\u00e9xico",
        "final_address": "Location marker\n07310\nCandelaria Ticoman Ciudad de M\u00e9xico, CDMX, M\u00e9xico",
        "platform": "ubereats"
    },
    {
        "text": "Da Vinci\nDa Vinci\n4.8\n(1,000+)\n \u2022 \n45 min",
        "href": "https://www.ubereats.com/mx/store/da-vinci/fH1_yPbURs2VYL3t0MGQQA",
        "cate_source": "populares_cerca",
        "current_address": "07310, Ciudad de M\u00e9xico",
        "final_address": "Location marker\n07310\nCandelaria Ticoman Ciudad de M\u00e9xico, CDMX, M\u00e9xico",
        "platform": "ubereats"
    },
    {
        "text": "Taqueria Puerto Mixe Oaxaca.\nTaqueria Puerto Mixe Oaxaca.\n4.6\n(3,000+)\n \u2022 \n40 min",
        "href": "https://www.ubereats.com/mx/store/taqueria-puerto-mixe-oaxaca/wxECt2jYQAezSsLJUeI_NQ",
        "cate_source": "populares_cerca",
        "current_address": "07310, Ciudad de M\u00e9xico",
        "final_address": "Location marker\n07310\nCandelaria Ticoman Ciudad de M\u00e9xico, CDMX, M\u00e9xico",
        "platform": "ubereats"
    },
    {
        "text": "TASTY GREENS\nGasta $349, ahorra $80\nTASTY GREENS\n4.7\n(390+)\n \u2022 \n50 min",
        "href": "https://www.ubereats.com/mx/store/tasty-greens-parque-lindavista/NVhLV1-yVKagwYulURS9qg",
        "cate_source": "populares_cerca",
        "current_address": "07310, Ciudad de M\u00e9xico",
        "final_address": "Location marker\n07310\nCandelaria Ticoman Ciudad de M\u00e9xico, CDMX, M\u00e9xico",
        "platform": "ubereats"
    },
    {
        "text": "Food Truck 7 brazas\nFood Truck 7 brazas\n4.6\n(500+)\n \u2022 \n25 min",
        "href": "https://www.ubereats.com/mx/store/food-truck-7-brazas/oMDKmo1xSvqK6alcso7tEw",
        "cate_source": "populares_cerca",
        "current_address": "07310, Ciudad de M\u00e9xico",
        "final_address": "Location marker\n07310\nCandelaria Ticoman Ciudad de M\u00e9xico, CDMX, M\u00e9xico",
        "platform": "ubereats"
    },
    {
        "text": "Las brasitas mixe\nLas brasitas mixe\n4.7\n(130+)\n \u2022 \n25 min",
        "href": "https://www.ubereats.com/mx/store/las-brasitas-mixe/NksYYoopUeiLUj44BMqjpg",
        "cate_source": "populares_cerca",
        "current_address": "07310, Ciudad de M\u00e9xico",
        "final_address": "Location marker\n07310\nCandelaria Ticoman Ciudad de M\u00e9xico, CDMX, M\u00e9xico",
        "platform": "ubereats"
    },
    {
        "text": "Panaderia Ochoa\nGasta $160, ahorra $45\nPanaderia Ochoa\n4.8\n(500+)\n \u2022 \n30 min",
        "href": "https://www.ubereats.com/mx/store/panaderia-ochoa/JQHYCVh7WLOOYE7AlOEmJQ",
        "cate_source": "populares_cerca",
        "current_address": "07310, Ciudad de M\u00e9xico",
        "final_address": "Location marker\n07310\nCandelaria Ticoman Ciudad de M\u00e9xico, CDMX, M\u00e9xico",
        "platform": "ubereats"
    },
    {
        "text": "El Charco de Las Ranas Lindavista\nEl Charco de Las Ranas Lindavista\n4.5\n(2,000+)\n \u2022 \n40 min",
        "href": "https://www.ubereats.com/mx/store/el-charco-de-las-ranas-lindavista/NFsL1i_UQkWv7g83OxEfMg",
        "cate_source": "populares_cerca",
        "current_address": "07310, Ciudad de M\u00e9xico",
        "final_address": "Location marker\n07310\nCandelaria Ticoman Ciudad de M\u00e9xico, CDMX, M\u00e9xico",
        "platform": "ubereats"
    },
    {
        "text": "Parrilla Argentina el 10 Fast\nParrilla Argentina el 10 Fast\n4.2\n(1,000+)\n \u2022 \n45 min",
        "href": "https://www.ubereats.com/mx/store/parrilla-argentina-el-10-fast/CB89zV1RQ6SGQuvzLxTwFw",
        "cate_source": "populares_cerca",
        "current_address": "07310, Ciudad de M\u00e9xico",
        "final_address": "Location marker\n07310\nCandelaria Ticoman Ciudad de M\u00e9xico, CDMX, M\u00e9xico",
        "platform": "ubereats"
    },
    {
        "text": "Mis Dulces Tentaciones\nOferta superior \u2022 2X1\nMis Dulces Tentaciones\n4.6\n(91)\n \u2022 \n35 min",
        "href": "https://www.ubereats.com/mx/store/mis-dulces-tentaciones/JeQU60GwRXaXSfZsjVek8Q",
        "cate_source": "populares_cerca",
        "current_address": "07310, Ciudad de M\u00e9xico",
        "final_address": "Location marker\n07310\nCandelaria Ticoman Ciudad de M\u00e9xico, CDMX, M\u00e9xico",
        "platform": "ubereats"
    },
    {
        "text": "Marisqueria La Bamba\nMarisqueria La Bamba\n4.3\n(1,000+)\n \u2022 \n40 min",
        "href": "https://www.ubereats.com/mx/store/marisqueria-la-bamba-mexico-city/98YJ-7Z6Q5yLLnWUEq__bg",
        "cate_source": "populares_cerca",
        "current_address": "07310, Ciudad de M\u00e9xico",
        "final_address": "Location marker\n07310\nCandelaria Ticoman Ciudad de M\u00e9xico, CDMX, M\u00e9xico",
        "platform": "ubereats"
    },
    {
        "text": "Samytortas\nSamytortas\n4.7\n(1,500+)\n \u2022 \n35 min",
        "href": "https://www.ubereats.com/mx/store/samytortas/IiIQWtFIT7GQ5_jnvMxE_w",
        "cate_source": "populares_cerca",
        "current_address": "07310, Ciudad de M\u00e9xico",
        "final_address": "Location marker\n07310\nCandelaria Ticoman Ciudad de M\u00e9xico, CDMX, M\u00e9xico",
        "platform": "ubereats"
    },
    {
        "text": "Emilio's Pizza & Wings\nEmilio's Pizza & Wings",
        "href": "https://www.ubereats.com/mx/store/emilios-pizza-%26-wings/mX0DMR6yV5mUKqQnTQy-Iw",
        "cate_source": "populares_cerca",
        "current_address": "07310, Ciudad de M\u00e9xico",
        "final_address": "Location marker\n07310\nCandelaria Ticoman Ciudad de M\u00e9xico, CDMX, M\u00e9xico",
        "platform": "ubereats"
    },
    {
        "text": "EL GATO ROJO\nEL GATO ROJO\n4.7\n(800+)\n \u2022 \n40 min",
        "href": "https://www.ubereats.com/mx/store/el-gato-rojo/wZ22GzAIRTG07nP7WNE_Rg",
        "cate_source": "populares_cerca",
        "current_address": "07310, Ciudad de M\u00e9xico",
        "final_address": "Location marker\n07310\nCandelaria Ticoman Ciudad de M\u00e9xico, CDMX, M\u00e9xico",
        "platform": "ubereats"
    },
    {
        "text": "Donibuena\nAhorros exclusivos\nDonibuena\n4.4\n(230+)\n \u2022 \n45 min",
        "href": "https://www.ubereats.com/mx/store/donibuena-cuautepec/Pr-ZVcu1Q4WBluvymvP-Bw",
        "cate_source": "populares_cerca",
        "current_address": "07310, Ciudad de M\u00e9xico",
        "final_address": "Location marker\n07310\nCandelaria Ticoman Ciudad de M\u00e9xico, CDMX, M\u00e9xico",
        "platform": "ubereats"
    },
    {
        "text": "Caf\u00e9 de Natal\nCaf\u00e9 de Natal\n4.8\n(140+)\n \u2022 \n45 min",
        "href": "https://www.ubereats.com/mx/store/cafe-de-natal/nH7_WaRCRY-xziojGixR0Q",
        "cate_source": "populares_cerca",
        "current_address": "07310, Ciudad de M\u00e9xico",
        "final_address": "Location marker\n07310\nCandelaria Ticoman Ciudad de M\u00e9xico, CDMX, M\u00e9xico",
        "platform": "ubereats"
    },
    {
        "text": "Los Huicholes\nAhorros exclusivos\nLos Huicholes\n4.3\n(2,000+)\n \u2022 \n35 min",
        "href": "https://www.ubereats.com/mx/store/los-huicholes/ZmNQ0NElRCyeY2QL23n_2w",
        "cate_source": "populares_cerca",
        "current_address": "07310, Ciudad de M\u00e9xico",
        "final_address": "Location marker\n07310\nCandelaria Ticoman Ciudad de M\u00e9xico, CDMX, M\u00e9xico",
        "platform": "ubereats"
    },
    {
        "text": "Tortas Tahona\nTortas Tahona\n4.7\n(600+)\n \u2022 \n40 min",
        "href": "https://www.ubereats.com/mx/store/tortas-tahona/c7eJDJXcTAePgfC0ezL4DQ",
        "cate_source": "populares_cerca",
        "current_address": "07310, Ciudad de M\u00e9xico",
        "final_address": "Location marker\n07310\nCandelaria Ticoman Ciudad de M\u00e9xico, CDMX, M\u00e9xico",
        "platform": "ubereats"
    },
    {
        "text": "Casa de los Hojaldres Montevideo\nCasa de los Hojaldres Montevideo\n4.9\n(160+)\n \u2022 \n35 min",
        "href": "https://www.ubereats.com/mx/store/casa-de-los-hojaldres-montevideo/kxT_2bFXRsKPfuPvTjZX9Q",
        "cate_source": "populares_cerca",
        "current_address": "07310, Ciudad de M\u00e9xico",
        "final_address": "Location marker\n07310\nCandelaria Ticoman Ciudad de M\u00e9xico, CDMX, M\u00e9xico",
        "platform": "ubereats"
    },
    {
        "text": "Dulce Antojo\nDulce Antojo\n3.6\n(29)\n \u2022 \n40 min",
        "href": "https://www.ubereats.com/mx/store/dulce-antojo/VMOdNgN6W16Biea95FOCPw",
        "cate_source": "populares_cerca",
        "current_address": "07310, Ciudad de M\u00e9xico",
        "final_address": "Location marker\n07310\nCandelaria Ticoman Ciudad de M\u00e9xico, CDMX, M\u00e9xico",
        "platform": "ubereats"
    },
    {
        "text": "LA ENSALADERA\nLA ENSALADERA\n4.4\n(23)\n \u2022 \n35 min",
        "href": "https://www.ubereats.com/mx/store/la-ensaladera/dSGt2fp5Wky1-wqWl_RLww",
        "cate_source": "populares_cerca",
        "current_address": "07310, Ciudad de M\u00e9xico",
        "final_address": "Location marker\n07310\nCandelaria Ticoman Ciudad de M\u00e9xico, CDMX, M\u00e9xico",
        "platform": "ubereats"
    },
    {
        "text": "Oliva Negra Pizzer\u00eda\nOliva Negra Pizzer\u00eda\n4.7\n(470+)\n \u2022 \n55 min",
        "href": "https://www.ubereats.com/mx/store/oliva-negra-pizzeria/ZjdoOWxqT2KeQPYlCFTTiA",
        "cate_source": "populares_cerca",
        "current_address": "07310, Ciudad de M\u00e9xico",
        "final_address": "Location marker\n07310\nCandelaria Ticoman Ciudad de M\u00e9xico, CDMX, M\u00e9xico",
        "platform": "ubereats"
    },
    {
        "text": "La Octava Caf\u00e9\nLa Octava Caf\u00e9\n4.7\n(15)\n \u2022 \n35 min",
        "href": "https://www.ubereats.com/mx/store/la-octava-cafe-lindavista/hw1pfupGUZG3tEZrcIrULg",
        "cate_source": "populares_cerca",
        "current_address": "07310, Ciudad de M\u00e9xico",
        "final_address": "Location marker\n07310\nCandelaria Ticoman Ciudad de M\u00e9xico, CDMX, M\u00e9xico",
        "platform": "ubereats"
    },
    {
        "text": "China Food Wus\nChina Food Wus\n4.7\n(2,000+)\n \u2022 \n40 min",
        "href": "https://www.ubereats.com/mx/store/china-food-wus-colector/UjUe-meLQ5S79SwpqpFSmg",
        "cate_source": "populares_cerca",
        "current_address": "07310, Ciudad de M\u00e9xico",
        "final_address": "Location marker\n07310\nCandelaria Ticoman Ciudad de M\u00e9xico, CDMX, M\u00e9xico",
        "platform": "ubereats"
    },
    {
        "text": "Alingo Lingo\nAlingo Lingo\n4.7\n(1,500+)\n \u2022 \n45 min",
        "href": "https://www.ubereats.com/mx/store/alingo-lingo/VyN5BLljTs64IN5k0C3oiw",
        "cate_source": "populares_cerca",
        "current_address": "07310, Ciudad de M\u00e9xico",
        "final_address": "Location marker\n07310\nCandelaria Ticoman Ciudad de M\u00e9xico, CDMX, M\u00e9xico",
        "platform": "ubereats"
    },
    {
        "text": "Suki Sushi\nCosto de env\u00edo de $0 (gasto de $100)\nSuki Sushi",
        "href": "https://www.ubereats.com/mx/store/suki-sushi-mexico-city/u9998BmGUJSF1h3J93k7Fg",
        "cate_source": "populares_cerca",
        "current_address": "07310, Ciudad de M\u00e9xico",
        "final_address": "Location marker\n07310\nCandelaria Ticoman Ciudad de M\u00e9xico, CDMX, M\u00e9xico",
        "platform": "ubereats"
    },
    {
        "text": "Karitzy\nKaritzy\n4.8\n(2,000+)\n \u2022 \n40 min",
        "href": "https://www.ubereats.com/mx/store/karitzy/Tzk7MU_3TCekcw-SNhcVhA",
        "cate_source": "populares_cerca",
        "current_address": "07310, Ciudad de M\u00e9xico",
        "final_address": "Location marker\n07310\nCandelaria Ticoman Ciudad de M\u00e9xico, CDMX, M\u00e9xico",
        "platform": "ubereats"
    },
    {
        "text": "La Rockola 353\nAhorros exclusivos\nLa Rockola 353\n4.5\n(800+)\n \u2022 \n35 min",
        "href": "https://www.ubereats.com/mx/store/la-rockola-353/JEw2SKwKStKlr9zJzXkbUw",
        "cate_source": "populares_cerca",
        "current_address": "07310, Ciudad de M\u00e9xico",
        "final_address": "Location marker\n07310\nCandelaria Ticoman Ciudad de M\u00e9xico, CDMX, M\u00e9xico",
        "platform": "ubereats"
    }
]