[
    {
        "text": "Rocking Burgers Santa Ana\nRocking Burgers Santa Ana\n4.8\n(4,000+)\n \u2022 \n20 min",
        "href": "https://www.ubereats.com/mx/store/rocking-burgers-santa-ana/HBo3yALtSDm5pFMFPA-PrA",
        "cate_source": "populares_cerca",
        "current_address": "09820, Ciudad de M\u00e9xico",
        "final_address": "Location marker\n09820\nRicardo Flores Mag\u00f3n Ciudad de M\u00e9xico, CDMX, M\u00e9xico",
        "platform": "ubereats"
    },
    {
        "text": "El Naranjito\nAhorros exclusivos\nEl Naranjito\n4.6\n(10,000+)\n \u2022 \n25 min",
        "href": "https://www.ubereats.com/mx/store/el-naranjito-eje-8/pZ-xaSJmQXeuKlC8ZxNFug",
        "cate_source": "populares_cerca",
        "current_address": "09820, Ciudad de M\u00e9xico",
        "final_address": "Location marker\n09820\nRicardo Flores Mag\u00f3n Ciudad de M\u00e9xico, CDMX, M\u00e9xico",
        "platform": "ubereats"
    },
    {
        "text": "Creper\u00eda 201\nAhorros exclusivos\nCreper\u00eda 201\n4.8\n(4,000+)\n \u2022 \n10 min",
        "href": "https://www.ubereats.com/mx/store/creperia-201/rew72cdfSAmwhdUzn_sglw",
        "cate_source": "populares_cerca",
        "current_address": "09820, Ciudad de M\u00e9xico",
        "final_address": "Location marker\n09820\nRicardo Flores Mag\u00f3n Ciudad de M\u00e9xico, CDMX, M\u00e9xico",
        "platform": "ubereats"
    },
    {
        "text": "Taqueria Los Tioss\nOferta superior \u2022 2 Ofertas disponibles\nTaqueria Los Tioss\n4.6\n(5,000+)\n \u2022 \n25 min",
        "href": "https://www.ubereats.com/mx/store/taqueria-los-tioss/6K-bmxXCSb--sIyUx_7DuQ",
        "cate_source": "populares_cerca",
        "current_address": "09820, Ciudad de M\u00e9xico",
        "final_address": "Location marker\n09820\nRicardo Flores Mag\u00f3n Ciudad de M\u00e9xico, CDMX, M\u00e9xico",
        "platform": "ubereats"
    },
    {
        "text": "Taqueria Los G\u00fceros\nTaqueria Los G\u00fceros\n4.3\n(6,000+)\n \u2022 \n20 min",
        "href": "https://www.ubereats.com/mx/store/taqueria-los-gueros-suc-plutarco/U9od5jYISXak2zPJj_sbQw",
        "cate_source": "populares_cerca",
        "current_address": "09820, Ciudad de M\u00e9xico",
        "final_address": "Location marker\n09820\nRicardo Flores Mag\u00f3n Ciudad de M\u00e9xico, CDMX, M\u00e9xico",
        "platform": "ubereats"
    },
    {
        "text": "Tacos Los Chavos\nTacos Los Chavos\n4.7\n(6,000+)\n \u2022 \n30 min",
        "href": "https://www.ubereats.com/mx/store/tacos-los-chavos/FL5BqjplSjyLZ98c60ygyA",
        "cate_source": "populares_cerca",
        "current_address": "09820, Ciudad de M\u00e9xico",
        "final_address": "Location marker\n09820\nRicardo Flores Mag\u00f3n Ciudad de M\u00e9xico, CDMX, M\u00e9xico",
        "platform": "ubereats"
    },
    {
        "text": "Hamburguesas Gigantes DD\nOferta superior \u2022 2 Ofertas disponibles\nHamburguesas Gigantes DD\n4.6\n(700+)\n \u2022 \n25 min",
        "href": "https://www.ubereats.com/mx/store/hamburguesas-gigantes-dd/I1oiPjfrRn-c51XFTPtkcw",
        "cate_source": "populares_cerca",
        "current_address": "09820, Ciudad de M\u00e9xico",
        "final_address": "Location marker\n09820\nRicardo Flores Mag\u00f3n Ciudad de M\u00e9xico, CDMX, M\u00e9xico",
        "platform": "ubereats"
    },
    {
        "text": "Los Sifones\nLos Sifones\n4.8\n(10,000+)\n \u2022 \n25 min",
        "href": "https://www.ubereats.com/mx/store/los-sifones/e14oxLljTmq4HtTT8nFlQA",
        "cate_source": "populares_cerca",
        "current_address": "09820, Ciudad de M\u00e9xico",
        "final_address": "Location marker\n09820\nRicardo Flores Mag\u00f3n Ciudad de M\u00e9xico, CDMX, M\u00e9xico",
        "platform": "ubereats"
    },
    {
        "text": "PRESIDENTE CREPER\u00cdAS\nOferta superior \u2022 2 Ofertas disponibles\nPRESIDENTE CREPER\u00cdAS\n4.8\n(800+)\n \u2022 \n20 min",
        "href": "https://www.ubereats.com/mx/store/presidente-creperias/orSa-wm9U6uTQzNXA9NehA",
        "cate_source": "populares_cerca",
        "current_address": "09820, Ciudad de M\u00e9xico",
        "final_address": "Location marker\n09820\nRicardo Flores Mag\u00f3n Ciudad de M\u00e9xico, CDMX, M\u00e9xico",
        "platform": "ubereats"
    },
    {
        "text": "Sushi Izakaya Punto Maq\nAhorros exclusivos\nSushi Izakaya Punto Maq\n4.4\n(250+)\n \u2022 \n40 min",
        "href": "https://www.ubereats.com/mx/store/sushi-izakaya-punto-maq/SIdwr0v-UGSGornA17VwWw",
        "cate_source": "populares_cerca",
        "current_address": "09820, Ciudad de M\u00e9xico",
        "final_address": "Location marker\n09820\nRicardo Flores Mag\u00f3n Ciudad de M\u00e9xico, CDMX, M\u00e9xico",
        "platform": "ubereats"
    },
    {
        "text": "Happy Food Sector Popular\nOferta superior \u2022 2 Ofertas disponibles\nHappy Food Sector Popular\n4.8\n(2,000+)\n \u2022 \n20 min",
        "href": "https://www.ubereats.com/mx/store/happy-food-sector-popular/hx6KJ468Tne5Cs6ppbgZfw",
        "cate_source": "populares_cerca",
        "current_address": "09820, Ciudad de M\u00e9xico",
        "final_address": "Location marker\n09820\nRicardo Flores Mag\u00f3n Ciudad de M\u00e9xico, CDMX, M\u00e9xico",
        "platform": "ubereats"
    },
    {
        "text": "Taco 911\nOferta superior \u2022 Ahorros exclusivos\nTaco 911\n4.5\n(5,000+)\n \u2022 \n25 min",
        "href": "https://www.ubereats.com/mx/store/taco-911-churubusco/wPiHLCZ6ThKsKSTUQl7taA",
        "cate_source": "populares_cerca",
        "current_address": "09820, Ciudad de M\u00e9xico",
        "final_address": "Location marker\n09820\nRicardo Flores Mag\u00f3n Ciudad de M\u00e9xico, CDMX, M\u00e9xico",
        "platform": "ubereats"
    },
    {
        "text": "La Posta Parrilla\nLa Posta Parrilla\n4.8\n(2,000+)\n \u2022 \n40 min",
        "href": "https://www.ubereats.com/mx/store/la-posta-parrilla/utjDWt6fQ0eKBOqHQZ-qdg",
        "cate_source": "populares_cerca",
        "current_address": "09820, Ciudad de M\u00e9xico",
        "final_address": "Location marker\n09820\nRicardo Flores Mag\u00f3n Ciudad de M\u00e9xico, CDMX, M\u00e9xico",
        "platform": "ubereats"
    },
    {
        "text": "El Rancho de Don Juan\nEl Rancho de Don Juan\n4.5\n(3,000+)\n \u2022 \n30 min",
        "href": "https://www.ubereats.com/mx/store/el-rancho-de-don-juan-1/Lvx-8CydQreri9Dz7e3jxQ",
        "cate_source": "populares_cerca",
        "current_address": "09820, Ciudad de M\u00e9xico",
        "final_address": "Location marker\n09820\nRicardo Flores Mag\u00f3n Ciudad de M\u00e9xico, CDMX, M\u00e9xico",
        "platform": "ubereats"
    },
    {
        "text": "Alitas desveladas\nOferta superior \u2022 Ahorros exclusivos\nAlitas desveladas\n4.2\n(340+)\n \u2022 \n40 min",
        "href": "https://www.ubereats.com/mx/store/alitas-desveladas/arcY6R99XASR-8v1kqtGeA",
        "cate_source": "populares_cerca",
        "current_address": "09820, Ciudad de M\u00e9xico",
        "final_address": "Location marker\n09820\nRicardo Flores Mag\u00f3n Ciudad de M\u00e9xico, CDMX, M\u00e9xico",
        "platform": "ubereats"
    },
    {
        "text": "Alitas y Boneless para desvelados\nOferta superior \u2022 Ahorros exclusivos\nAlitas y Boneless para desvelados\n4.3\n(260+)\n \u2022 \n20 min",
        "href": "https://www.ubereats.com/mx/store/alitas-y-boneless-para-desvelados/4f8N1sUNQ8ySraDNEGMRzw",
        "cate_source": "populares_cerca",
        "current_address": "09820, Ciudad de M\u00e9xico",
        "final_address": "Location marker\n09820\nRicardo Flores Mag\u00f3n Ciudad de M\u00e9xico, CDMX, M\u00e9xico",
        "platform": "ubereats"
    },
    {
        "text": "Toki Maki Sushi\nOferta superior \u2022 Ahorros exclusivos\nToki Maki Sushi\n4.7\n(4,000+)\n \u2022 \n25 min",
        "href": "https://www.ubereats.com/mx/store/toki-maki-sushi/lV9ySxD6RvGSIjQ3qEpyLQ",
        "cate_source": "populares_cerca",
        "current_address": "09820, Ciudad de M\u00e9xico",
        "final_address": "Location marker\n09820\nRicardo Flores Mag\u00f3n Ciudad de M\u00e9xico, CDMX, M\u00e9xico",
        "platform": "ubereats"
    },
    {
        "text": "El Burro de Moctezuma\nEl Burro de Moctezuma\n4.7\n(10,000+)\n \u2022 \n40 min",
        "href": "https://www.ubereats.com/mx/store/el-burro-de-moctezuma/RzH89QRHRRKhH4ccd3UDRw",
        "cate_source": "populares_cerca",
        "current_address": "09820, Ciudad de M\u00e9xico",
        "final_address": "Location marker\n09820\nRicardo Flores Mag\u00f3n Ciudad de M\u00e9xico, CDMX, M\u00e9xico",
        "platform": "ubereats"
    },
    {
        "text": "Tommy Burger\nOferta superior \u2022 2 Ofertas disponibles\nTommy Burger\n4.6\n(3,000+)\n \u2022 \n10 min",
        "href": "https://www.ubereats.com/mx/store/tommy-burger/iC_lZc-iSoGcaJInFCJx3A",
        "cate_source": "populares_cerca",
        "current_address": "09820, Ciudad de M\u00e9xico",
        "final_address": "Location marker\n09820\nRicardo Flores Mag\u00f3n Ciudad de M\u00e9xico, CDMX, M\u00e9xico",
        "platform": "ubereats"
    },
    {
        "text": "Caf\u00e9 Kowloon Div del Norte\nCaf\u00e9 Kowloon Div del Norte\n4.7\n(2,000+)\n \u2022 \n30 min",
        "href": "https://www.ubereats.com/mx/store/cafe-kowloon-div-del-norte/8Yq4oYrzQFyvCmKNOYrQsQ",
        "cate_source": "populares_cerca",
        "current_address": "09820, Ciudad de M\u00e9xico",
        "final_address": "Location marker\n09820\nRicardo Flores Mag\u00f3n Ciudad de M\u00e9xico, CDMX, M\u00e9xico",
        "platform": "ubereats"
    },
    {
        "text": "Las Baguettes de la Lagunilla\" coapa\"\nLas Baguettes de la Lagunilla\" coapa\"\n4.6\n(470+)\n \u2022 \n50 min",
        "href": "https://www.ubereats.com/mx/store/las-baguettes-de-la-lagunilla%22-coapa%22/Fyg-3OnrWVWW2i1j4DhdmQ",
        "cate_source": "populares_cerca",
        "current_address": "09820, Ciudad de M\u00e9xico",
        "final_address": "Location marker\n09820\nRicardo Flores Mag\u00f3n Ciudad de M\u00e9xico, CDMX, M\u00e9xico",
        "platform": "ubereats"
    },
    {
        "text": "Radici Pizza Napolitana\nOferta superior \u2022 Ahorros exclusivos\nRadici Pizza Napolitana\n4.6\n(1,000+)\n \u2022 \n35 min",
        "href": "https://www.ubereats.com/mx/store/radici-pizza-napolitana/SAAoXWdkXyiNhKiqDBfCbA",
        "cate_source": "populares_cerca",
        "current_address": "09820, Ciudad de M\u00e9xico",
        "final_address": "Location marker\n09820\nRicardo Flores Mag\u00f3n Ciudad de M\u00e9xico, CDMX, M\u00e9xico",
        "platform": "ubereats"
    },
    {
        "text": "Taqueria el Compa Coyoac\u00e1n\nOferta superior \u2022 2 Ofertas disponibles\nTaqueria el Compa Coyoac\u00e1n\n4.7\n(6,000+)\n \u2022 \n20 min",
        "href": "https://www.ubereats.com/mx/store/taqueria-el-compa-coyoacan-div-del-norte/ltqZW5ySRPaus3mPR8t15Q",
        "cate_source": "populares_cerca",
        "current_address": "09820, Ciudad de M\u00e9xico",
        "final_address": "Location marker\n09820\nRicardo Flores Mag\u00f3n Ciudad de M\u00e9xico, CDMX, M\u00e9xico",
        "platform": "ubereats"
    },
    {
        "text": "Los Sopes de la Nueve\nLos Sopes de la Nueve\n4.7\n(10,000+)\n \u2022 \n25 min",
        "href": "https://www.ubereats.com/mx/store/los-sopes-de-la-nueve/bmeItbdXQTWixBKbibxjWg",
        "cate_source": "populares_cerca",
        "current_address": "09820, Ciudad de M\u00e9xico",
        "final_address": "Location marker\n09820\nRicardo Flores Mag\u00f3n Ciudad de M\u00e9xico, CDMX, M\u00e9xico",
        "platform": "ubereats"
    },
    {
        "text": "Alitas Maestras Tezontle\nOferta superior \u2022 Ahorros exclusivos\nAlitas Maestras Tezontle\n4.3\n(200+)\n \u2022 \n40 min",
        "href": "https://www.ubereats.com/mx/store/alitas-maestras-tezontle/ChjOin6mXoSNssKyyGpMNg",
        "cate_source": "populares_cerca",
        "current_address": "09820, Ciudad de M\u00e9xico",
        "final_address": "Location marker\n09820\nRicardo Flores Mag\u00f3n Ciudad de M\u00e9xico, CDMX, M\u00e9xico",
        "platform": "ubereats"
    },
    {
        "text": "480\u00b0 Pizza Lounge Coyoac\u00e1n\n480\u00b0 Pizza Lounge Coyoac\u00e1n\n4.7\n(5,000+)\n \u2022 \n30 min",
        "href": "https://www.ubereats.com/mx/store/480-pizza-lounge-coyoacan/Cf2Z2cDhRSGDKrYZoSiJJA",
        "cate_source": "populares_cerca",
        "current_address": "09820, Ciudad de M\u00e9xico",
        "final_address": "Location marker\n09820\nRicardo Flores Mag\u00f3n Ciudad de M\u00e9xico, CDMX, M\u00e9xico",
        "platform": "ubereats"
    },
    {
        "text": "Hostal de los Quesos\nHostal de los Quesos\n4.8\n(10,000+)\n \u2022 \n45 min",
        "href": "https://www.ubereats.com/mx/store/hostal-de-los-quesos/O3aTahxDQTazv7RxpyOzjw",
        "cate_source": "populares_cerca",
        "current_address": "09820, Ciudad de M\u00e9xico",
        "final_address": "Location marker\n09820\nRicardo Flores Mag\u00f3n Ciudad de M\u00e9xico, CDMX, M\u00e9xico",
        "platform": "ubereats"
    },
    {
        "text": "Pipiris Fries\nPipiris Fries\n4.8\n(2,000+)\n \u2022 \n25 min",
        "href": "https://www.ubereats.com/mx/store/pipiris-fries/E2Qc5_i0QcGWA9tjANTweA",
        "cate_source": "populares_cerca",
        "current_address": "09820, Ciudad de M\u00e9xico",
        "final_address": "Location marker\n09820\nRicardo Flores Mag\u00f3n Ciudad de M\u00e9xico, CDMX, M\u00e9xico",
        "platform": "ubereats"
    },
    {
        "text": "Tortas del Barrio Zapata\n2 Ofertas disponibles\nTortas del Barrio Zapata\n4.4\n(120+)\n \u2022 \n25 min",
        "href": "https://www.ubereats.com/mx/store/tortas-del-barrio-zapata/XJO1dVf9XnuPTAk3oXjf-g",
        "cate_source": "populares_cerca",
        "current_address": "09820, Ciudad de M\u00e9xico",
        "final_address": "Location marker\n09820\nRicardo Flores Mag\u00f3n Ciudad de M\u00e9xico, CDMX, M\u00e9xico",
        "platform": "ubereats"
    },
    {
        "text": "Tort-as\nOferta superior \u2022 Gasta $350, ahorra $105\nTort-as\n4.7\n(4,000+)\n \u2022 \n20 min",
        "href": "https://www.ubereats.com/mx/store/tort-as/wSAR_ynZQxenAqQR0CwasA",
        "cate_source": "populares_cerca",
        "current_address": "09820, Ciudad de M\u00e9xico",
        "final_address": "Location marker\n09820\nRicardo Flores Mag\u00f3n Ciudad de M\u00e9xico, CDMX, M\u00e9xico",
        "platform": "ubereats"
    },
    {
        "text": "Pozoleria Flor de Maiz\nPozoleria Flor de Maiz\n4.5\n(350+)\n \u2022 \n35 min",
        "href": "https://www.ubereats.com/mx/store/pozoleria-flor-de-maiz-coruna/vb6DYM7SVRaG0J-oJQtIYQ",
        "cate_source": "populares_cerca",
        "current_address": "09820, Ciudad de M\u00e9xico",
        "final_address": "Location marker\n09820\nRicardo Flores Mag\u00f3n Ciudad de M\u00e9xico, CDMX, M\u00e9xico",
        "platform": "ubereats"
    },
    {
        "text": "A Darle Que Es Taco Vegano\nA Darle Que Es Taco Vegano\n4.9\n(2,000+)\n \u2022 \n30 min",
        "href": "https://www.ubereats.com/mx/store/a-darle-que-es-taco-vegano/tyEHbE3fRTqyexUGDUcw9Q",
        "cate_source": "populares_cerca",
        "current_address": "09820, Ciudad de M\u00e9xico",
        "final_address": "Location marker\n09820\nRicardo Flores Mag\u00f3n Ciudad de M\u00e9xico, CDMX, M\u00e9xico",
        "platform": "ubereats"
    },
    {
        "text": "El Ma\u00edz Azteca\nOferta superior \u2022 Ahorros exclusivos\nEl Ma\u00edz Azteca\n4.1\n(5,000+)\n \u2022 \n40 min",
        "href": "https://www.ubereats.com/mx/store/el-maiz-azteca/II3tAyPIR2e-xMRrPnMn9Q",
        "cate_source": "populares_cerca",
        "current_address": "09820, Ciudad de M\u00e9xico",
        "final_address": "Location marker\n09820\nRicardo Flores Mag\u00f3n Ciudad de M\u00e9xico, CDMX, M\u00e9xico",
        "platform": "ubereats"
    },
    {
        "text": "Salvaxe Nativitas Pizzer\u00eda vegana\nSalvaxe Nativitas Pizzer\u00eda vegana\n4.8\n(360+)\n \u2022 \n35 min",
        "href": "https://www.ubereats.com/mx/store/salvaxe-nativitas-pizzeria-vegana/9VKh7EspQ66eF6DezpI8SQ",
        "cate_source": "populares_cerca",
        "current_address": "09820, Ciudad de M\u00e9xico",
        "final_address": "Location marker\n09820\nRicardo Flores Mag\u00f3n Ciudad de M\u00e9xico, CDMX, M\u00e9xico",
        "platform": "ubereats"
    },
    {
        "text": "Umami Roll\nUmami Roll\n4.7\n(3,000+)\n \u2022 \n30 min",
        "href": "https://www.ubereats.com/mx/store/umami-roll/CWrdiid7R1S_vaJb7YrmHA",
        "cate_source": "populares_cerca",
        "current_address": "09820, Ciudad de M\u00e9xico",
        "final_address": "Location marker\n09820\nRicardo Flores Mag\u00f3n Ciudad de M\u00e9xico, CDMX, M\u00e9xico",
        "platform": "ubereats"
    },
    {
        "text": "Caf\u00e9 Ka\u00b4Loc Plaza Churubusco\nCosto de env\u00edo de $0 (gasto de $100)\nCaf\u00e9 Ka\u00b4Loc Plaza Churubusco\n4.8\n(140+)\n \u2022 \n20 min",
        "href": "https://www.ubereats.com/mx/store/cafe-ka-loc-plaza-churubusco/phQ8UcoBQ_WqMHVOdBWJyA",
        "cate_source": "populares_cerca",
        "current_address": "09820, Ciudad de M\u00e9xico",
        "final_address": "Location marker\n09820\nRicardo Flores Mag\u00f3n Ciudad de M\u00e9xico, CDMX, M\u00e9xico",
        "platform": "ubereats"
    },
    {
        "text": "Crepa Roll\nCrepa Roll\n4.7\n(1,500+)\n \u2022 \n40 min",
        "href": "https://www.ubereats.com/mx/store/crepa-roll/zhzP4Re3QUa_JJ41CMuxxw",
        "cate_source": "populares_cerca",
        "current_address": "09820, Ciudad de M\u00e9xico",
        "final_address": "Location marker\n09820\nRicardo Flores Mag\u00f3n Ciudad de M\u00e9xico, CDMX, M\u00e9xico",
        "platform": "ubereats"
    },
    {
        "text": "El Trompito\nEl Trompito\n4.4\n(1,500+)\n \u2022 \n20 min",
        "href": "https://www.ubereats.com/mx/store/el-trompito/6nKR4-DPTL2ecjpMBluUeQ",
        "cate_source": "populares_cerca",
        "current_address": "09820, Ciudad de M\u00e9xico",
        "final_address": "Location marker\n09820\nRicardo Flores Mag\u00f3n Ciudad de M\u00e9xico, CDMX, M\u00e9xico",
        "platform": "ubereats"
    },
    {
        "text": "La Malteader\u00eda Portales\nLa Malteader\u00eda Portales\n4.8\n(600+)\n \u2022 \n25 min",
        "href": "https://www.ubereats.com/mx/store/la-malteaderia-portales/nrQUC5Y-V_Wxv8rNQ1_6CA",
        "cate_source": "populares_cerca",
        "current_address": "09820, Ciudad de M\u00e9xico",
        "final_address": "Location marker\n09820\nRicardo Flores Mag\u00f3n Ciudad de M\u00e9xico, CDMX, M\u00e9xico",
        "platform": "ubereats"
    },
    {
        "text": "Boneless Night\nBoneless Night\n4.1\n(600+)\n \u2022 \n25 min",
        "href": "https://www.ubereats.com/mx/store/boneless-night/-EsBUZYVSiijn44BEXhRLw",
        "cate_source": "populares_cerca",
        "current_address": "09820, Ciudad de M\u00e9xico",
        "final_address": "Location marker\n09820\nRicardo Flores Mag\u00f3n Ciudad de M\u00e9xico, CDMX, M\u00e9xico",
        "platform": "ubereats"
    }
]